<?xml version="1.0" encoding="UTF-8"?>
<!--
  PLN Jamali State Estimation — CIM Equipment Profile (EQ)
  IEC 61970-552 / CGMES 3.0  |  Modelling Authority: PT PLN (Persero)
  Network: Jamali 150/20 kV region (Cirata – Cibinong – Depok – Gandul –
           Bekasi – Bogor), 10 buses, 6 lines, 4 transformers
  Generated by: generate_cim_iec61850.py
  mRID scheme:  UUID5(DNS-NS, "pln.co.id/jamali-se/{tag}")
-->
<rdf:RDF xmlns:rdf="http://www.w3.org/1999/02/22-rdf-syntax-ns#"
  xmlns:cim="http://iec.ch/TC57/CIM100#"
  xmlns:md="http://iec.ch/TC57/61970-552/ModelDescription/1#"
  xmlns:xsd="http://www.w3.org/2001/XMLSchema#">

  <md:FullModel rdf:about="urn:uuid:7fcc86b4-b426-5172-8930-6ffcc6eda84f">
    <md:Model.profile>http://iec.ch/TC57/ns/CIM/CoreEquipment-EU/2.0</md:Model.profile>
    <md:Model.modelingAuthoritySet>http://www.pln.co.id/</md:Model.modelingAuthoritySet>
    <md:Model.description>PLN Jamali 150/20 kV WLS state estimation test network</md:Model.description>
    <md:Model.version>2.0</md:Model.version>
  </md:FullModel>
  <!-- ═══ BaseVoltages ═══════════════════════════════════════════ -->
  <cim:BaseVoltage rdf:about="urn:uuid:d41fde42-d533-5df0-9005-d2c799b7dd54">
    <cim:IdentifiedObject.mRID>d41fde42-d533-5df0-9005-d2c799b7dd54</cim:IdentifiedObject.mRID>
    <cim:IdentifiedObject.name>150 kV</cim:IdentifiedObject.name>
    <cim:BaseVoltage.nominalVoltage rdf:datatype="http://www.w3.org/2001/XMLSchema#float">150000.0</cim:BaseVoltage.nominalVoltage>
  </cim:BaseVoltage>

  <cim:BaseVoltage rdf:about="urn:uuid:9c31ca86-75f2-51ed-b0c2-8905f1317026">
    <cim:IdentifiedObject.mRID>9c31ca86-75f2-51ed-b0c2-8905f1317026</cim:IdentifiedObject.mRID>
    <cim:IdentifiedObject.name>20 kV</cim:IdentifiedObject.name>
    <cim:BaseVoltage.nominalVoltage rdf:datatype="http://www.w3.org/2001/XMLSchema#float">20000.0</cim:BaseVoltage.nominalVoltage>
  </cim:BaseVoltage>

  <!-- ═══ Substations ═════════════════════════════════════════════ -->
  <cim:Substation rdf:about="urn:uuid:8e3a87a2-834d-55d6-906a-5e2b97168518">
    <cim:IdentifiedObject.mRID>8e3a87a2-834d-55d6-906a-5e2b97168518</cim:IdentifiedObject.mRID>
    <cim:IdentifiedObject.name>GI Cirata</cim:IdentifiedObject.name>
    <cim:IdentifiedObject.description>IEC 61850 B1=0ADCIR  IED=IED_CIR</cim:IdentifiedObject.description>
  </cim:Substation>

  <cim:Substation rdf:about="urn:uuid:6a94fd8f-c759-50d7-b234-a351c81736c5">
    <cim:IdentifiedObject.mRID>6a94fd8f-c759-50d7-b234-a351c81736c5</cim:IdentifiedObject.mRID>
    <cim:IdentifiedObject.name>GI Cibinong</cim:IdentifiedObject.name>
    <cim:IdentifiedObject.description>IEC 61850 B1=0ADCBN  IED=IED_CBN</cim:IdentifiedObject.description>
  </cim:Substation>

  <cim:Substation rdf:about="urn:uuid:a3ee3c50-5dbd-5dea-a8b9-8c421fc28bf7">
    <cim:IdentifiedObject.mRID>a3ee3c50-5dbd-5dea-a8b9-8c421fc28bf7</cim:IdentifiedObject.mRID>
    <cim:IdentifiedObject.name>GI Depok</cim:IdentifiedObject.name>
    <cim:IdentifiedObject.description>IEC 61850 B1=0ADDPK  IED=IED_DPK</cim:IdentifiedObject.description>
  </cim:Substation>

  <cim:Substation rdf:about="urn:uuid:5cab8724-f722-583c-a3fc-a3db14fc518f">
    <cim:IdentifiedObject.mRID>5cab8724-f722-583c-a3fc-a3db14fc518f</cim:IdentifiedObject.mRID>
    <cim:IdentifiedObject.name>GI Gandul</cim:IdentifiedObject.name>
    <cim:IdentifiedObject.description>IEC 61850 B1=0ADGND  IED=IED_GND</cim:IdentifiedObject.description>
  </cim:Substation>

  <cim:Substation rdf:about="urn:uuid:0943f3ff-32fa-508e-ba17-fe849ebb7d60">
    <cim:IdentifiedObject.mRID>0943f3ff-32fa-508e-ba17-fe849ebb7d60</cim:IdentifiedObject.mRID>
    <cim:IdentifiedObject.name>GI Bekasi</cim:IdentifiedObject.name>
    <cim:IdentifiedObject.description>IEC 61850 B1=0ADBKS  IED=IED_BKS</cim:IdentifiedObject.description>
  </cim:Substation>

  <cim:Substation rdf:about="urn:uuid:d44c3253-2ac9-5cf2-a1be-b6af738d7521">
    <cim:IdentifiedObject.mRID>d44c3253-2ac9-5cf2-a1be-b6af738d7521</cim:IdentifiedObject.mRID>
    <cim:IdentifiedObject.name>GI Bogor</cim:IdentifiedObject.name>
    <cim:IdentifiedObject.description>IEC 61850 B1=0ADBGR  IED=IED_BGR</cim:IdentifiedObject.description>
  </cim:Substation>

  <!-- ═══ VoltageLevels ════════════════════════════════════════════ -->
  <cim:VoltageLevel rdf:about="urn:uuid:18f93598-4ba1-5ff9-830b-b88557984275">
    <cim:IdentifiedObject.mRID>18f93598-4ba1-5ff9-830b-b88557984275</cim:IdentifiedObject.mRID>
    <cim:IdentifiedObject.name>CIRATA 150 kV</cim:IdentifiedObject.name>
    <cim:VoltageLevel.Substation rdf:resource="urn:uuid:8e3a87a2-834d-55d6-906a-5e2b97168518"/>
    <cim:VoltageLevel.BaseVoltage rdf:resource="urn:uuid:d41fde42-d533-5df0-9005-d2c799b7dd54"/>
  </cim:VoltageLevel>

  <cim:VoltageLevel rdf:about="urn:uuid:12153ee0-6d30-5a9d-a3e8-06f2774c325c">
    <cim:IdentifiedObject.mRID>12153ee0-6d30-5a9d-a3e8-06f2774c325c</cim:IdentifiedObject.mRID>
    <cim:IdentifiedObject.name>CIBINONG 150 kV</cim:IdentifiedObject.name>
    <cim:VoltageLevel.Substation rdf:resource="urn:uuid:6a94fd8f-c759-50d7-b234-a351c81736c5"/>
    <cim:VoltageLevel.BaseVoltage rdf:resource="urn:uuid:d41fde42-d533-5df0-9005-d2c799b7dd54"/>
  </cim:VoltageLevel>

  <cim:VoltageLevel rdf:about="urn:uuid:d4853f90-2b6a-5335-bcf2-3dc12d4f703a">
    <cim:IdentifiedObject.mRID>d4853f90-2b6a-5335-bcf2-3dc12d4f703a</cim:IdentifiedObject.mRID>
    <cim:IdentifiedObject.name>DEPOK 150 kV</cim:IdentifiedObject.name>
    <cim:VoltageLevel.Substation rdf:resource="urn:uuid:a3ee3c50-5dbd-5dea-a8b9-8c421fc28bf7"/>
    <cim:VoltageLevel.BaseVoltage rdf:resource="urn:uuid:d41fde42-d533-5df0-9005-d2c799b7dd54"/>
  </cim:VoltageLevel>

  <cim:VoltageLevel rdf:about="urn:uuid:af5ef4f4-472e-5d58-8076-a79f26510709">
    <cim:IdentifiedObject.mRID>af5ef4f4-472e-5d58-8076-a79f26510709</cim:IdentifiedObject.mRID>
    <cim:IdentifiedObject.name>GANDUL 150 kV</cim:IdentifiedObject.name>
    <cim:VoltageLevel.Substation rdf:resource="urn:uuid:5cab8724-f722-583c-a3fc-a3db14fc518f"/>
    <cim:VoltageLevel.BaseVoltage rdf:resource="urn:uuid:d41fde42-d533-5df0-9005-d2c799b7dd54"/>
  </cim:VoltageLevel>

  <cim:VoltageLevel rdf:about="urn:uuid:602b5736-68ed-55c1-837c-d90e85c46d32">
    <cim:IdentifiedObject.mRID>602b5736-68ed-55c1-837c-d90e85c46d32</cim:IdentifiedObject.mRID>
    <cim:IdentifiedObject.name>CIBINONG 20 kV</cim:IdentifiedObject.name>
    <cim:VoltageLevel.Substation rdf:resource="urn:uuid:6a94fd8f-c759-50d7-b234-a351c81736c5"/>
    <cim:VoltageLevel.BaseVoltage rdf:resource="urn:uuid:9c31ca86-75f2-51ed-b0c2-8905f1317026"/>
  </cim:VoltageLevel>

  <cim:VoltageLevel rdf:about="urn:uuid:0aa8ee52-cffd-5fdc-9ba6-10d202642ff7">
    <cim:IdentifiedObject.mRID>0aa8ee52-cffd-5fdc-9ba6-10d202642ff7</cim:IdentifiedObject.mRID>
    <cim:IdentifiedObject.name>DEPOK 20 kV</cim:IdentifiedObject.name>
    <cim:VoltageLevel.Substation rdf:resource="urn:uuid:a3ee3c50-5dbd-5dea-a8b9-8c421fc28bf7"/>
    <cim:VoltageLevel.BaseVoltage rdf:resource="urn:uuid:9c31ca86-75f2-51ed-b0c2-8905f1317026"/>
  </cim:VoltageLevel>

  <cim:VoltageLevel rdf:about="urn:uuid:2eceb80d-2cdf-5de7-886b-20a9f97d36bc">
    <cim:IdentifiedObject.mRID>2eceb80d-2cdf-5de7-886b-20a9f97d36bc</cim:IdentifiedObject.mRID>
    <cim:IdentifiedObject.name>BEKASI 150 kV</cim:IdentifiedObject.name>
    <cim:VoltageLevel.Substation rdf:resource="urn:uuid:0943f3ff-32fa-508e-ba17-fe849ebb7d60"/>
    <cim:VoltageLevel.BaseVoltage rdf:resource="urn:uuid:d41fde42-d533-5df0-9005-d2c799b7dd54"/>
  </cim:VoltageLevel>

  <cim:VoltageLevel rdf:about="urn:uuid:37ba2394-5296-54bb-9b40-746732adde52">
    <cim:IdentifiedObject.mRID>37ba2394-5296-54bb-9b40-746732adde52</cim:IdentifiedObject.mRID>
    <cim:IdentifiedObject.name>BEKASI 20 kV</cim:IdentifiedObject.name>
    <cim:VoltageLevel.Substation rdf:resource="urn:uuid:0943f3ff-32fa-508e-ba17-fe849ebb7d60"/>
    <cim:VoltageLevel.BaseVoltage rdf:resource="urn:uuid:9c31ca86-75f2-51ed-b0c2-8905f1317026"/>
  </cim:VoltageLevel>

  <cim:VoltageLevel rdf:about="urn:uuid:d5030fdf-26e6-5862-9072-263636e89021">
    <cim:IdentifiedObject.mRID>d5030fdf-26e6-5862-9072-263636e89021</cim:IdentifiedObject.mRID>
    <cim:IdentifiedObject.name>BOGOR 150 kV</cim:IdentifiedObject.name>
    <cim:VoltageLevel.Substation rdf:resource="urn:uuid:d44c3253-2ac9-5cf2-a1be-b6af738d7521"/>
    <cim:VoltageLevel.BaseVoltage rdf:resource="urn:uuid:d41fde42-d533-5df0-9005-d2c799b7dd54"/>
  </cim:VoltageLevel>

  <cim:VoltageLevel rdf:about="urn:uuid:8bc865ba-da79-5bff-8667-b95bfe2142ca">
    <cim:IdentifiedObject.mRID>8bc865ba-da79-5bff-8667-b95bfe2142ca</cim:IdentifiedObject.mRID>
    <cim:IdentifiedObject.name>BOGOR 20 kV</cim:IdentifiedObject.name>
    <cim:VoltageLevel.Substation rdf:resource="urn:uuid:d44c3253-2ac9-5cf2-a1be-b6af738d7521"/>
    <cim:VoltageLevel.BaseVoltage rdf:resource="urn:uuid:9c31ca86-75f2-51ed-b0c2-8905f1317026"/>
  </cim:VoltageLevel>

  <!-- ═══ ConnectivityNodes (bus) ══════════════════════════════════ -->
  <cim:ConnectivityNode rdf:about="urn:uuid:f9dcd3a5-3c4f-534b-8ec4-eec6d2b759b5">
    <cim:IdentifiedObject.mRID>f9dcd3a5-3c4f-534b-8ec4-eec6d2b759b5</cim:IdentifiedObject.mRID>
    <cim:IdentifiedObject.name>CIRATA_150</cim:IdentifiedObject.name>
    <cim:ConnectivityNode.ConnectivityNodeContainer rdf:resource="urn:uuid:18f93598-4ba1-5ff9-830b-b88557984275"/>
  </cim:ConnectivityNode>

  <cim:ConnectivityNode rdf:about="urn:uuid:ea2b29a1-ee88-5d8b-9823-d81e4b4862bd">
    <cim:IdentifiedObject.mRID>ea2b29a1-ee88-5d8b-9823-d81e4b4862bd</cim:IdentifiedObject.mRID>
    <cim:IdentifiedObject.name>CIBINONG_150</cim:IdentifiedObject.name>
    <cim:ConnectivityNode.ConnectivityNodeContainer rdf:resource="urn:uuid:12153ee0-6d30-5a9d-a3e8-06f2774c325c"/>
  </cim:ConnectivityNode>

  <cim:ConnectivityNode rdf:about="urn:uuid:1f3e1ca9-ac27-54ce-add4-7c325df64b6e">
    <cim:IdentifiedObject.mRID>1f3e1ca9-ac27-54ce-add4-7c325df64b6e</cim:IdentifiedObject.mRID>
    <cim:IdentifiedObject.name>DEPOK_150</cim:IdentifiedObject.name>
    <cim:ConnectivityNode.ConnectivityNodeContainer rdf:resource="urn:uuid:d4853f90-2b6a-5335-bcf2-3dc12d4f703a"/>
  </cim:ConnectivityNode>

  <cim:ConnectivityNode rdf:about="urn:uuid:2946c071-12c0-5d7e-a0a7-26c203e85154">
    <cim:IdentifiedObject.mRID>2946c071-12c0-5d7e-a0a7-26c203e85154</cim:IdentifiedObject.mRID>
    <cim:IdentifiedObject.name>GANDUL_150</cim:IdentifiedObject.name>
    <cim:ConnectivityNode.ConnectivityNodeContainer rdf:resource="urn:uuid:af5ef4f4-472e-5d58-8076-a79f26510709"/>
  </cim:ConnectivityNode>

  <cim:ConnectivityNode rdf:about="urn:uuid:0ffdf116-5420-5535-baf2-3b2157e218fb">
    <cim:IdentifiedObject.mRID>0ffdf116-5420-5535-baf2-3b2157e218fb</cim:IdentifiedObject.mRID>
    <cim:IdentifiedObject.name>CIBINONG_20</cim:IdentifiedObject.name>
    <cim:ConnectivityNode.ConnectivityNodeContainer rdf:resource="urn:uuid:602b5736-68ed-55c1-837c-d90e85c46d32"/>
  </cim:ConnectivityNode>

  <cim:ConnectivityNode rdf:about="urn:uuid:e4db7411-ace7-519c-8103-b9bd48d1d95c">
    <cim:IdentifiedObject.mRID>e4db7411-ace7-519c-8103-b9bd48d1d95c</cim:IdentifiedObject.mRID>
    <cim:IdentifiedObject.name>DEPOK_20</cim:IdentifiedObject.name>
    <cim:ConnectivityNode.ConnectivityNodeContainer rdf:resource="urn:uuid:0aa8ee52-cffd-5fdc-9ba6-10d202642ff7"/>
  </cim:ConnectivityNode>

  <cim:ConnectivityNode rdf:about="urn:uuid:1698b030-c9b7-5770-8e63-8bf6cff14a60">
    <cim:IdentifiedObject.mRID>1698b030-c9b7-5770-8e63-8bf6cff14a60</cim:IdentifiedObject.mRID>
    <cim:IdentifiedObject.name>BEKASI_150</cim:IdentifiedObject.name>
    <cim:ConnectivityNode.ConnectivityNodeContainer rdf:resource="urn:uuid:2eceb80d-2cdf-5de7-886b-20a9f97d36bc"/>
  </cim:ConnectivityNode>

  <cim:ConnectivityNode rdf:about="urn:uuid:2ed59b45-5650-5677-9958-5d9b2dffe1dc">
    <cim:IdentifiedObject.mRID>2ed59b45-5650-5677-9958-5d9b2dffe1dc</cim:IdentifiedObject.mRID>
    <cim:IdentifiedObject.name>BEKASI_20</cim:IdentifiedObject.name>
    <cim:ConnectivityNode.ConnectivityNodeContainer rdf:resource="urn:uuid:37ba2394-5296-54bb-9b40-746732adde52"/>
  </cim:ConnectivityNode>

  <cim:ConnectivityNode rdf:about="urn:uuid:115dbc85-7583-50b0-97e9-0ee2281c0967">
    <cim:IdentifiedObject.mRID>115dbc85-7583-50b0-97e9-0ee2281c0967</cim:IdentifiedObject.mRID>
    <cim:IdentifiedObject.name>BOGOR_150</cim:IdentifiedObject.name>
    <cim:ConnectivityNode.ConnectivityNodeContainer rdf:resource="urn:uuid:d5030fdf-26e6-5862-9072-263636e89021"/>
  </cim:ConnectivityNode>

  <cim:ConnectivityNode rdf:about="urn:uuid:90035e27-51c2-54fb-8d8c-c6ba0539c67d">
    <cim:IdentifiedObject.mRID>90035e27-51c2-54fb-8d8c-c6ba0539c67d</cim:IdentifiedObject.mRID>
    <cim:IdentifiedObject.name>BOGOR_20</cim:IdentifiedObject.name>
    <cim:ConnectivityNode.ConnectivityNodeContainer rdf:resource="urn:uuid:8bc865ba-da79-5bff-8667-b95bfe2142ca"/>
  </cim:ConnectivityNode>

  <!-- ═══ ConnectivityNodes (feeder, breaker-inserted) ═════════════ -->
  <cim:ConnectivityNode rdf:about="urn:uuid:804de988-b55a-54ae-a525-115dd8d4e707">
    <cim:IdentifiedObject.mRID>804de988-b55a-54ae-a525-115dd8d4e707</cim:IdentifiedObject.mRID>
    <cim:IdentifiedObject.name>Feeder CN CB_CIRATA_L1</cim:IdentifiedObject.name>
    <cim:ConnectivityNode.ConnectivityNodeContainer rdf:resource="urn:uuid:18f93598-4ba1-5ff9-830b-b88557984275"/>
  </cim:ConnectivityNode>

  <cim:ConnectivityNode rdf:about="urn:uuid:6c2ff010-14f3-5bfd-aded-cfdad2bf9eb3">
    <cim:IdentifiedObject.mRID>6c2ff010-14f3-5bfd-aded-cfdad2bf9eb3</cim:IdentifiedObject.mRID>
    <cim:IdentifiedObject.name>Feeder CN CB_CIBINONG_L1</cim:IdentifiedObject.name>
    <cim:ConnectivityNode.ConnectivityNodeContainer rdf:resource="urn:uuid:12153ee0-6d30-5a9d-a3e8-06f2774c325c"/>
  </cim:ConnectivityNode>

  <cim:ConnectivityNode rdf:about="urn:uuid:d61e38c9-ee84-58a3-a456-e0a63b5efeff">
    <cim:IdentifiedObject.mRID>d61e38c9-ee84-58a3-a456-e0a63b5efeff</cim:IdentifiedObject.mRID>
    <cim:IdentifiedObject.name>Feeder CN CB_CIBINONG_L2</cim:IdentifiedObject.name>
    <cim:ConnectivityNode.ConnectivityNodeContainer rdf:resource="urn:uuid:12153ee0-6d30-5a9d-a3e8-06f2774c325c"/>
  </cim:ConnectivityNode>

  <cim:ConnectivityNode rdf:about="urn:uuid:21d72021-a619-5cc0-8793-3f0339b59421">
    <cim:IdentifiedObject.mRID>21d72021-a619-5cc0-8793-3f0339b59421</cim:IdentifiedObject.mRID>
    <cim:IdentifiedObject.name>Feeder CN CB_DEPOK_L2</cim:IdentifiedObject.name>
    <cim:ConnectivityNode.ConnectivityNodeContainer rdf:resource="urn:uuid:d4853f90-2b6a-5335-bcf2-3dc12d4f703a"/>
  </cim:ConnectivityNode>

  <cim:ConnectivityNode rdf:about="urn:uuid:727902ba-0b84-5ec7-90db-38dc036a6d92">
    <cim:IdentifiedObject.mRID>727902ba-0b84-5ec7-90db-38dc036a6d92</cim:IdentifiedObject.mRID>
    <cim:IdentifiedObject.name>Feeder CN CB_CIBINONG_T1</cim:IdentifiedObject.name>
    <cim:ConnectivityNode.ConnectivityNodeContainer rdf:resource="urn:uuid:12153ee0-6d30-5a9d-a3e8-06f2774c325c"/>
  </cim:ConnectivityNode>

  <cim:ConnectivityNode rdf:about="urn:uuid:58f59bde-fd94-5dd5-8c75-6203bfd5b59c">
    <cim:IdentifiedObject.mRID>58f59bde-fd94-5dd5-8c75-6203bfd5b59c</cim:IdentifiedObject.mRID>
    <cim:IdentifiedObject.name>Feeder CN CB_DEPOK_T2</cim:IdentifiedObject.name>
    <cim:ConnectivityNode.ConnectivityNodeContainer rdf:resource="urn:uuid:d4853f90-2b6a-5335-bcf2-3dc12d4f703a"/>
  </cim:ConnectivityNode>

  <!-- ═══ BusbarSections ═══════════════════════════════════════════ -->
  <cim:BusbarSection rdf:about="urn:uuid:aecf6693-f21d-54e1-ad62-0998667f337d">
    <cim:IdentifiedObject.mRID>aecf6693-f21d-54e1-ad62-0998667f337d</cim:IdentifiedObject.mRID>
    <cim:IdentifiedObject.name>BB_CIRATA_150</cim:IdentifiedObject.name>
    <cim:Equipment.EquipmentContainer rdf:resource="urn:uuid:18f93598-4ba1-5ff9-830b-b88557984275"/>
    <cim:Equipment.inService rdf:datatype="http://www.w3.org/2001/XMLSchema#boolean">true</cim:Equipment.inService>
  </cim:BusbarSection>

  <cim:Terminal rdf:about="urn:uuid:052acf94-7cf3-59a6-a3e7-568b0776827a">
    <cim:IdentifiedObject.mRID>052acf94-7cf3-59a6-a3e7-568b0776827a</cim:IdentifiedObject.mRID>
    <cim:IdentifiedObject.name>T_BB1_1</cim:IdentifiedObject.name>
    <cim:Terminal.ConductingEquipment rdf:resource="urn:uuid:aecf6693-f21d-54e1-ad62-0998667f337d"/>
    <cim:Terminal.ConnectivityNode rdf:resource="urn:uuid:f9dcd3a5-3c4f-534b-8ec4-eec6d2b759b5"/>
    <cim:ACDCTerminal.sequenceNumber rdf:datatype="http://www.w3.org/2001/XMLSchema#integer">1</cim:ACDCTerminal.sequenceNumber>
    <cim:ACDCTerminal.connected rdf:datatype="http://www.w3.org/2001/XMLSchema#boolean">true</cim:ACDCTerminal.connected>
  </cim:Terminal>

  <cim:BusbarSection rdf:about="urn:uuid:14741336-7718-5888-951a-09b78f6f1f42">
    <cim:IdentifiedObject.mRID>14741336-7718-5888-951a-09b78f6f1f42</cim:IdentifiedObject.mRID>
    <cim:IdentifiedObject.name>BB_CIBINONG_150</cim:IdentifiedObject.name>
    <cim:Equipment.EquipmentContainer rdf:resource="urn:uuid:12153ee0-6d30-5a9d-a3e8-06f2774c325c"/>
    <cim:Equipment.inService rdf:datatype="http://www.w3.org/2001/XMLSchema#boolean">true</cim:Equipment.inService>
  </cim:BusbarSection>

  <cim:Terminal rdf:about="urn:uuid:9ca4611c-b4ba-518d-b462-43e7b3af3fad">
    <cim:IdentifiedObject.mRID>9ca4611c-b4ba-518d-b462-43e7b3af3fad</cim:IdentifiedObject.mRID>
    <cim:IdentifiedObject.name>T_BB2_1</cim:IdentifiedObject.name>
    <cim:Terminal.ConductingEquipment rdf:resource="urn:uuid:14741336-7718-5888-951a-09b78f6f1f42"/>
    <cim:Terminal.ConnectivityNode rdf:resource="urn:uuid:ea2b29a1-ee88-5d8b-9823-d81e4b4862bd"/>
    <cim:ACDCTerminal.sequenceNumber rdf:datatype="http://www.w3.org/2001/XMLSchema#integer">1</cim:ACDCTerminal.sequenceNumber>
    <cim:ACDCTerminal.connected rdf:datatype="http://www.w3.org/2001/XMLSchema#boolean">true</cim:ACDCTerminal.connected>
  </cim:Terminal>

  <cim:BusbarSection rdf:about="urn:uuid:9d328e8b-c766-50a7-b6fa-730af2d79ce7">
    <cim:IdentifiedObject.mRID>9d328e8b-c766-50a7-b6fa-730af2d79ce7</cim:IdentifiedObject.mRID>
    <cim:IdentifiedObject.name>BB_DEPOK_150</cim:IdentifiedObject.name>
    <cim:Equipment.EquipmentContainer rdf:resource="urn:uuid:d4853f90-2b6a-5335-bcf2-3dc12d4f703a"/>
    <cim:Equipment.inService rdf:datatype="http://www.w3.org/2001/XMLSchema#boolean">true</cim:Equipment.inService>
  </cim:BusbarSection>

  <cim:Terminal rdf:about="urn:uuid:718b555f-a968-5094-adb2-f3adba5ceed2">
    <cim:IdentifiedObject.mRID>718b555f-a968-5094-adb2-f3adba5ceed2</cim:IdentifiedObject.mRID>
    <cim:IdentifiedObject.name>T_BB3_1</cim:IdentifiedObject.name>
    <cim:Terminal.ConductingEquipment rdf:resource="urn:uuid:9d328e8b-c766-50a7-b6fa-730af2d79ce7"/>
    <cim:Terminal.ConnectivityNode rdf:resource="urn:uuid:1f3e1ca9-ac27-54ce-add4-7c325df64b6e"/>
    <cim:ACDCTerminal.sequenceNumber rdf:datatype="http://www.w3.org/2001/XMLSchema#integer">1</cim:ACDCTerminal.sequenceNumber>
    <cim:ACDCTerminal.connected rdf:datatype="http://www.w3.org/2001/XMLSchema#boolean">true</cim:ACDCTerminal.connected>
  </cim:Terminal>

  <cim:BusbarSection rdf:about="urn:uuid:86797214-0a6b-54bf-b271-c726ab8e2347">
    <cim:IdentifiedObject.mRID>86797214-0a6b-54bf-b271-c726ab8e2347</cim:IdentifiedObject.mRID>
    <cim:IdentifiedObject.name>BB_GANDUL_150</cim:IdentifiedObject.name>
    <cim:Equipment.EquipmentContainer rdf:resource="urn:uuid:af5ef4f4-472e-5d58-8076-a79f26510709"/>
    <cim:Equipment.inService rdf:datatype="http://www.w3.org/2001/XMLSchema#boolean">true</cim:Equipment.inService>
  </cim:BusbarSection>

  <cim:Terminal rdf:about="urn:uuid:c0253104-0554-5f77-abc7-dda59884eab4">
    <cim:IdentifiedObject.mRID>c0253104-0554-5f77-abc7-dda59884eab4</cim:IdentifiedObject.mRID>
    <cim:IdentifiedObject.name>T_BB4_1</cim:IdentifiedObject.name>
    <cim:Terminal.ConductingEquipment rdf:resource="urn:uuid:86797214-0a6b-54bf-b271-c726ab8e2347"/>
    <cim:Terminal.ConnectivityNode rdf:resource="urn:uuid:2946c071-12c0-5d7e-a0a7-26c203e85154"/>
    <cim:ACDCTerminal.sequenceNumber rdf:datatype="http://www.w3.org/2001/XMLSchema#integer">1</cim:ACDCTerminal.sequenceNumber>
    <cim:ACDCTerminal.connected rdf:datatype="http://www.w3.org/2001/XMLSchema#boolean">true</cim:ACDCTerminal.connected>
  </cim:Terminal>

  <cim:BusbarSection rdf:about="urn:uuid:e3e319c0-47c5-5ff5-a6f1-6958d4279f9b">
    <cim:IdentifiedObject.mRID>e3e319c0-47c5-5ff5-a6f1-6958d4279f9b</cim:IdentifiedObject.mRID>
    <cim:IdentifiedObject.name>BB_CIBINONG_20</cim:IdentifiedObject.name>
    <cim:Equipment.EquipmentContainer rdf:resource="urn:uuid:602b5736-68ed-55c1-837c-d90e85c46d32"/>
    <cim:Equipment.inService rdf:datatype="http://www.w3.org/2001/XMLSchema#boolean">true</cim:Equipment.inService>
  </cim:BusbarSection>

  <cim:Terminal rdf:about="urn:uuid:acf15770-36f0-576f-802f-7895bf36eb0d">
    <cim:IdentifiedObject.mRID>acf15770-36f0-576f-802f-7895bf36eb0d</cim:IdentifiedObject.mRID>
    <cim:IdentifiedObject.name>T_BB5_1</cim:IdentifiedObject.name>
    <cim:Terminal.ConductingEquipment rdf:resource="urn:uuid:e3e319c0-47c5-5ff5-a6f1-6958d4279f9b"/>
    <cim:Terminal.ConnectivityNode rdf:resource="urn:uuid:0ffdf116-5420-5535-baf2-3b2157e218fb"/>
    <cim:ACDCTerminal.sequenceNumber rdf:datatype="http://www.w3.org/2001/XMLSchema#integer">1</cim:ACDCTerminal.sequenceNumber>
    <cim:ACDCTerminal.connected rdf:datatype="http://www.w3.org/2001/XMLSchema#boolean">true</cim:ACDCTerminal.connected>
  </cim:Terminal>

  <cim:BusbarSection rdf:about="urn:uuid:448e7211-6ab5-56b9-b36b-e06b82317cf2">
    <cim:IdentifiedObject.mRID>448e7211-6ab5-56b9-b36b-e06b82317cf2</cim:IdentifiedObject.mRID>
    <cim:IdentifiedObject.name>BB_DEPOK_20</cim:IdentifiedObject.name>
    <cim:Equipment.EquipmentContainer rdf:resource="urn:uuid:0aa8ee52-cffd-5fdc-9ba6-10d202642ff7"/>
    <cim:Equipment.inService rdf:datatype="http://www.w3.org/2001/XMLSchema#boolean">true</cim:Equipment.inService>
  </cim:BusbarSection>

  <cim:Terminal rdf:about="urn:uuid:fc4d646a-7b71-5164-bc25-113fbd80d556">
    <cim:IdentifiedObject.mRID>fc4d646a-7b71-5164-bc25-113fbd80d556</cim:IdentifiedObject.mRID>
    <cim:IdentifiedObject.name>T_BB6_1</cim:IdentifiedObject.name>
    <cim:Terminal.ConductingEquipment rdf:resource="urn:uuid:448e7211-6ab5-56b9-b36b-e06b82317cf2"/>
    <cim:Terminal.ConnectivityNode rdf:resource="urn:uuid:e4db7411-ace7-519c-8103-b9bd48d1d95c"/>
    <cim:ACDCTerminal.sequenceNumber rdf:datatype="http://www.w3.org/2001/XMLSchema#integer">1</cim:ACDCTerminal.sequenceNumber>
    <cim:ACDCTerminal.connected rdf:datatype="http://www.w3.org/2001/XMLSchema#boolean">true</cim:ACDCTerminal.connected>
  </cim:Terminal>

  <cim:BusbarSection rdf:about="urn:uuid:c35ff9dd-a392-57e1-a602-6750705204f3">
    <cim:IdentifiedObject.mRID>c35ff9dd-a392-57e1-a602-6750705204f3</cim:IdentifiedObject.mRID>
    <cim:IdentifiedObject.name>BB_BEKASI_150</cim:IdentifiedObject.name>
    <cim:Equipment.EquipmentContainer rdf:resource="urn:uuid:2eceb80d-2cdf-5de7-886b-20a9f97d36bc"/>
    <cim:Equipment.inService rdf:datatype="http://www.w3.org/2001/XMLSchema#boolean">true</cim:Equipment.inService>
  </cim:BusbarSection>

  <cim:Terminal rdf:about="urn:uuid:370bd9c7-e9a2-5a65-942f-1792727abcc4">
    <cim:IdentifiedObject.mRID>370bd9c7-e9a2-5a65-942f-1792727abcc4</cim:IdentifiedObject.mRID>
    <cim:IdentifiedObject.name>T_BB7_1</cim:IdentifiedObject.name>
    <cim:Terminal.ConductingEquipment rdf:resource="urn:uuid:c35ff9dd-a392-57e1-a602-6750705204f3"/>
    <cim:Terminal.ConnectivityNode rdf:resource="urn:uuid:1698b030-c9b7-5770-8e63-8bf6cff14a60"/>
    <cim:ACDCTerminal.sequenceNumber rdf:datatype="http://www.w3.org/2001/XMLSchema#integer">1</cim:ACDCTerminal.sequenceNumber>
    <cim:ACDCTerminal.connected rdf:datatype="http://www.w3.org/2001/XMLSchema#boolean">true</cim:ACDCTerminal.connected>
  </cim:Terminal>

  <cim:BusbarSection rdf:about="urn:uuid:578cba21-6f21-579b-b7e6-c0230d05de0a">
    <cim:IdentifiedObject.mRID>578cba21-6f21-579b-b7e6-c0230d05de0a</cim:IdentifiedObject.mRID>
    <cim:IdentifiedObject.name>BB_BEKASI_20</cim:IdentifiedObject.name>
    <cim:Equipment.EquipmentContainer rdf:resource="urn:uuid:37ba2394-5296-54bb-9b40-746732adde52"/>
    <cim:Equipment.inService rdf:datatype="http://www.w3.org/2001/XMLSchema#boolean">true</cim:Equipment.inService>
  </cim:BusbarSection>

  <cim:Terminal rdf:about="urn:uuid:5e77b6af-e25f-5133-8386-2443fe3f7e54">
    <cim:IdentifiedObject.mRID>5e77b6af-e25f-5133-8386-2443fe3f7e54</cim:IdentifiedObject.mRID>
    <cim:IdentifiedObject.name>T_BB8_1</cim:IdentifiedObject.name>
    <cim:Terminal.ConductingEquipment rdf:resource="urn:uuid:578cba21-6f21-579b-b7e6-c0230d05de0a"/>
    <cim:Terminal.ConnectivityNode rdf:resource="urn:uuid:2ed59b45-5650-5677-9958-5d9b2dffe1dc"/>
    <cim:ACDCTerminal.sequenceNumber rdf:datatype="http://www.w3.org/2001/XMLSchema#integer">1</cim:ACDCTerminal.sequenceNumber>
    <cim:ACDCTerminal.connected rdf:datatype="http://www.w3.org/2001/XMLSchema#boolean">true</cim:ACDCTerminal.connected>
  </cim:Terminal>

  <cim:BusbarSection rdf:about="urn:uuid:a95447f6-ebff-55fa-9fb5-4833f03dd2d7">
    <cim:IdentifiedObject.mRID>a95447f6-ebff-55fa-9fb5-4833f03dd2d7</cim:IdentifiedObject.mRID>
    <cim:IdentifiedObject.name>BB_BOGOR_150</cim:IdentifiedObject.name>
    <cim:Equipment.EquipmentContainer rdf:resource="urn:uuid:d5030fdf-26e6-5862-9072-263636e89021"/>
    <cim:Equipment.inService rdf:datatype="http://www.w3.org/2001/XMLSchema#boolean">true</cim:Equipment.inService>
  </cim:BusbarSection>

  <cim:Terminal rdf:about="urn:uuid:db512362-df65-560a-9913-02f6365c7903">
    <cim:IdentifiedObject.mRID>db512362-df65-560a-9913-02f6365c7903</cim:IdentifiedObject.mRID>
    <cim:IdentifiedObject.name>T_BB9_1</cim:IdentifiedObject.name>
    <cim:Terminal.ConductingEquipment rdf:resource="urn:uuid:a95447f6-ebff-55fa-9fb5-4833f03dd2d7"/>
    <cim:Terminal.ConnectivityNode rdf:resource="urn:uuid:115dbc85-7583-50b0-97e9-0ee2281c0967"/>
    <cim:ACDCTerminal.sequenceNumber rdf:datatype="http://www.w3.org/2001/XMLSchema#integer">1</cim:ACDCTerminal.sequenceNumber>
    <cim:ACDCTerminal.connected rdf:datatype="http://www.w3.org/2001/XMLSchema#boolean">true</cim:ACDCTerminal.connected>
  </cim:Terminal>

  <cim:BusbarSection rdf:about="urn:uuid:1445dd16-414e-540f-8944-92a3dfdf0c49">
    <cim:IdentifiedObject.mRID>1445dd16-414e-540f-8944-92a3dfdf0c49</cim:IdentifiedObject.mRID>
    <cim:IdentifiedObject.name>BB_BOGOR_20</cim:IdentifiedObject.name>
    <cim:Equipment.EquipmentContainer rdf:resource="urn:uuid:8bc865ba-da79-5bff-8667-b95bfe2142ca"/>
    <cim:Equipment.inService rdf:datatype="http://www.w3.org/2001/XMLSchema#boolean">true</cim:Equipment.inService>
  </cim:BusbarSection>

  <cim:Terminal rdf:about="urn:uuid:8f64e964-bf65-563f-ba5b-c01f4d1fb05d">
    <cim:IdentifiedObject.mRID>8f64e964-bf65-563f-ba5b-c01f4d1fb05d</cim:IdentifiedObject.mRID>
    <cim:IdentifiedObject.name>T_BB10_1</cim:IdentifiedObject.name>
    <cim:Terminal.ConductingEquipment rdf:resource="urn:uuid:1445dd16-414e-540f-8944-92a3dfdf0c49"/>
    <cim:Terminal.ConnectivityNode rdf:resource="urn:uuid:90035e27-51c2-54fb-8d8c-c6ba0539c67d"/>
    <cim:ACDCTerminal.sequenceNumber rdf:datatype="http://www.w3.org/2001/XMLSchema#integer">1</cim:ACDCTerminal.sequenceNumber>
    <cim:ACDCTerminal.connected rdf:datatype="http://www.w3.org/2001/XMLSchema#boolean">true</cim:ACDCTerminal.connected>
  </cim:Terminal>

  <!-- ═══ ExternalNetworkInjection (slack bus at Cirata) ═══════════ -->
  <cim:ExternalNetworkInjection rdf:about="urn:uuid:5a9d81e5-1bd2-5bbc-b569-2c9ac3f05153">
    <cim:IdentifiedObject.mRID>5a9d81e5-1bd2-5bbc-b569-2c9ac3f05153</cim:IdentifiedObject.mRID>
    <cim:IdentifiedObject.name>SLACK_CIRATA</cim:IdentifiedObject.name>
    <cim:Equipment.EquipmentContainer rdf:resource="urn:uuid:18f93598-4ba1-5ff9-830b-b88557984275"/>
    <cim:Equipment.inService rdf:datatype="http://www.w3.org/2001/XMLSchema#boolean">true</cim:Equipment.inService>
    <cim:ExternalNetworkInjection.p rdf:datatype="http://www.w3.org/2001/XMLSchema#float">-155200000.0</cim:ExternalNetworkInjection.p>
    <cim:ExternalNetworkInjection.q rdf:datatype="http://www.w3.org/2001/XMLSchema#float">-32400000.0</cim:ExternalNetworkInjection.q>
    <cim:ExternalNetworkInjection.governorSCD rdf:datatype="http://www.w3.org/2001/XMLSchema#float">0.0</cim:ExternalNetworkInjection.governorSCD>
  </cim:ExternalNetworkInjection>

  <cim:Terminal rdf:about="urn:uuid:13e2cbb8-369b-5aab-8070-2d4f532823c9">
    <cim:IdentifiedObject.mRID>13e2cbb8-369b-5aab-8070-2d4f532823c9</cim:IdentifiedObject.mRID>
    <cim:IdentifiedObject.name>T_ENI_CIRATA_1</cim:IdentifiedObject.name>
    <cim:Terminal.ConductingEquipment rdf:resource="urn:uuid:5a9d81e5-1bd2-5bbc-b569-2c9ac3f05153"/>
    <cim:Terminal.ConnectivityNode rdf:resource="urn:uuid:f9dcd3a5-3c4f-534b-8ec4-eec6d2b759b5"/>
    <cim:ACDCTerminal.sequenceNumber rdf:datatype="http://www.w3.org/2001/XMLSchema#integer">1</cim:ACDCTerminal.sequenceNumber>
    <cim:ACDCTerminal.connected rdf:datatype="http://www.w3.org/2001/XMLSchema#boolean">true</cim:ACDCTerminal.connected>
  </cim:Terminal>

  <!-- ═══ Breakers (Circuit Breakers) ═════════════════════════════ -->
  <cim:Breaker rdf:about="urn:uuid:92cfe9b4-3dac-5332-b386-30fcb2ade09f">
    <cim:IdentifiedObject.mRID>92cfe9b4-3dac-5332-b386-30fcb2ade09f</cim:IdentifiedObject.mRID>
    <cim:IdentifiedObject.name>CB_CIRATA_L1</cim:IdentifiedObject.name>
    <cim:Equipment.EquipmentContainer rdf:resource="urn:uuid:18f93598-4ba1-5ff9-830b-b88557984275"/>
    <cim:Equipment.inService rdf:datatype="http://www.w3.org/2001/XMLSchema#boolean">true</cim:Equipment.inService>
    <cim:Switch.open rdf:datatype="http://www.w3.org/2001/XMLSchema#boolean">false</cim:Switch.open>
    <cim:Switch.normalOpen rdf:datatype="http://www.w3.org/2001/XMLSchema#boolean">false</cim:Switch.normalOpen>
    <cim:Switch.retained rdf:datatype="http://www.w3.org/2001/XMLSchema#boolean">true</cim:Switch.retained>
  </cim:Breaker>

  <cim:Terminal rdf:about="urn:uuid:85fe5b7d-b526-5742-b5f7-85c160f67a73">
    <cim:IdentifiedObject.mRID>85fe5b7d-b526-5742-b5f7-85c160f67a73</cim:IdentifiedObject.mRID>
    <cim:IdentifiedObject.name>T_CB_CIRATA_L1_1</cim:IdentifiedObject.name>
    <cim:Terminal.ConductingEquipment rdf:resource="urn:uuid:92cfe9b4-3dac-5332-b386-30fcb2ade09f"/>
    <cim:Terminal.ConnectivityNode rdf:resource="urn:uuid:f9dcd3a5-3c4f-534b-8ec4-eec6d2b759b5"/>
    <cim:ACDCTerminal.sequenceNumber rdf:datatype="http://www.w3.org/2001/XMLSchema#integer">1</cim:ACDCTerminal.sequenceNumber>
    <cim:ACDCTerminal.connected rdf:datatype="http://www.w3.org/2001/XMLSchema#boolean">true</cim:ACDCTerminal.connected>
  </cim:Terminal>

  <cim:Terminal rdf:about="urn:uuid:3c3d4532-60b4-5544-ab36-bc5e0c55173a">
    <cim:IdentifiedObject.mRID>3c3d4532-60b4-5544-ab36-bc5e0c55173a</cim:IdentifiedObject.mRID>
    <cim:IdentifiedObject.name>T_CB_CIRATA_L1_2</cim:IdentifiedObject.name>
    <cim:Terminal.ConductingEquipment rdf:resource="urn:uuid:92cfe9b4-3dac-5332-b386-30fcb2ade09f"/>
    <cim:Terminal.ConnectivityNode rdf:resource="urn:uuid:804de988-b55a-54ae-a525-115dd8d4e707"/>
    <cim:ACDCTerminal.sequenceNumber rdf:datatype="http://www.w3.org/2001/XMLSchema#integer">2</cim:ACDCTerminal.sequenceNumber>
    <cim:ACDCTerminal.connected rdf:datatype="http://www.w3.org/2001/XMLSchema#boolean">true</cim:ACDCTerminal.connected>
  </cim:Terminal>

  <cim:Breaker rdf:about="urn:uuid:4f76f1cb-94ac-5634-954a-01971caa6cab">
    <cim:IdentifiedObject.mRID>4f76f1cb-94ac-5634-954a-01971caa6cab</cim:IdentifiedObject.mRID>
    <cim:IdentifiedObject.name>CB_CIBINONG_L1</cim:IdentifiedObject.name>
    <cim:Equipment.EquipmentContainer rdf:resource="urn:uuid:12153ee0-6d30-5a9d-a3e8-06f2774c325c"/>
    <cim:Equipment.inService rdf:datatype="http://www.w3.org/2001/XMLSchema#boolean">true</cim:Equipment.inService>
    <cim:Switch.open rdf:datatype="http://www.w3.org/2001/XMLSchema#boolean">false</cim:Switch.open>
    <cim:Switch.normalOpen rdf:datatype="http://www.w3.org/2001/XMLSchema#boolean">false</cim:Switch.normalOpen>
    <cim:Switch.retained rdf:datatype="http://www.w3.org/2001/XMLSchema#boolean">true</cim:Switch.retained>
  </cim:Breaker>

  <cim:Terminal rdf:about="urn:uuid:351340d4-2ab7-5129-9ba0-6bb72b1aa637">
    <cim:IdentifiedObject.mRID>351340d4-2ab7-5129-9ba0-6bb72b1aa637</cim:IdentifiedObject.mRID>
    <cim:IdentifiedObject.name>T_CB_CIBINONG_L1_1</cim:IdentifiedObject.name>
    <cim:Terminal.ConductingEquipment rdf:resource="urn:uuid:4f76f1cb-94ac-5634-954a-01971caa6cab"/>
    <cim:Terminal.ConnectivityNode rdf:resource="urn:uuid:ea2b29a1-ee88-5d8b-9823-d81e4b4862bd"/>
    <cim:ACDCTerminal.sequenceNumber rdf:datatype="http://www.w3.org/2001/XMLSchema#integer">1</cim:ACDCTerminal.sequenceNumber>
    <cim:ACDCTerminal.connected rdf:datatype="http://www.w3.org/2001/XMLSchema#boolean">true</cim:ACDCTerminal.connected>
  </cim:Terminal>

  <cim:Terminal rdf:about="urn:uuid:0b80b590-8b6e-5619-b995-6a21f049efac">
    <cim:IdentifiedObject.mRID>0b80b590-8b6e-5619-b995-6a21f049efac</cim:IdentifiedObject.mRID>
    <cim:IdentifiedObject.name>T_CB_CIBINONG_L1_2</cim:IdentifiedObject.name>
    <cim:Terminal.ConductingEquipment rdf:resource="urn:uuid:4f76f1cb-94ac-5634-954a-01971caa6cab"/>
    <cim:Terminal.ConnectivityNode rdf:resource="urn:uuid:6c2ff010-14f3-5bfd-aded-cfdad2bf9eb3"/>
    <cim:ACDCTerminal.sequenceNumber rdf:datatype="http://www.w3.org/2001/XMLSchema#integer">2</cim:ACDCTerminal.sequenceNumber>
    <cim:ACDCTerminal.connected rdf:datatype="http://www.w3.org/2001/XMLSchema#boolean">true</cim:ACDCTerminal.connected>
  </cim:Terminal>

  <cim:Breaker rdf:about="urn:uuid:06cc5ce5-294e-5c9d-a857-97db94ed0d0e">
    <cim:IdentifiedObject.mRID>06cc5ce5-294e-5c9d-a857-97db94ed0d0e</cim:IdentifiedObject.mRID>
    <cim:IdentifiedObject.name>CB_CIBINONG_L2</cim:IdentifiedObject.name>
    <cim:Equipment.EquipmentContainer rdf:resource="urn:uuid:12153ee0-6d30-5a9d-a3e8-06f2774c325c"/>
    <cim:Equipment.inService rdf:datatype="http://www.w3.org/2001/XMLSchema#boolean">true</cim:Equipment.inService>
    <cim:Switch.open rdf:datatype="http://www.w3.org/2001/XMLSchema#boolean">false</cim:Switch.open>
    <cim:Switch.normalOpen rdf:datatype="http://www.w3.org/2001/XMLSchema#boolean">false</cim:Switch.normalOpen>
    <cim:Switch.retained rdf:datatype="http://www.w3.org/2001/XMLSchema#boolean">true</cim:Switch.retained>
  </cim:Breaker>

  <cim:Terminal rdf:about="urn:uuid:5b1038b9-2c2b-52e1-bef9-22cef58c4cc0">
    <cim:IdentifiedObject.mRID>5b1038b9-2c2b-52e1-bef9-22cef58c4cc0</cim:IdentifiedObject.mRID>
    <cim:IdentifiedObject.name>T_CB_CIBINONG_L2_1</cim:IdentifiedObject.name>
    <cim:Terminal.ConductingEquipment rdf:resource="urn:uuid:06cc5ce5-294e-5c9d-a857-97db94ed0d0e"/>
    <cim:Terminal.ConnectivityNode rdf:resource="urn:uuid:ea2b29a1-ee88-5d8b-9823-d81e4b4862bd"/>
    <cim:ACDCTerminal.sequenceNumber rdf:datatype="http://www.w3.org/2001/XMLSchema#integer">1</cim:ACDCTerminal.sequenceNumber>
    <cim:ACDCTerminal.connected rdf:datatype="http://www.w3.org/2001/XMLSchema#boolean">true</cim:ACDCTerminal.connected>
  </cim:Terminal>

  <cim:Terminal rdf:about="urn:uuid:4dc57be6-47b9-56c5-8c33-5e50ba54f644">
    <cim:IdentifiedObject.mRID>4dc57be6-47b9-56c5-8c33-5e50ba54f644</cim:IdentifiedObject.mRID>
    <cim:IdentifiedObject.name>T_CB_CIBINONG_L2_2</cim:IdentifiedObject.name>
    <cim:Terminal.ConductingEquipment rdf:resource="urn:uuid:06cc5ce5-294e-5c9d-a857-97db94ed0d0e"/>
    <cim:Terminal.ConnectivityNode rdf:resource="urn:uuid:d61e38c9-ee84-58a3-a456-e0a63b5efeff"/>
    <cim:ACDCTerminal.sequenceNumber rdf:datatype="http://www.w3.org/2001/XMLSchema#integer">2</cim:ACDCTerminal.sequenceNumber>
    <cim:ACDCTerminal.connected rdf:datatype="http://www.w3.org/2001/XMLSchema#boolean">true</cim:ACDCTerminal.connected>
  </cim:Terminal>

  <cim:Breaker rdf:about="urn:uuid:ba439cda-b55c-58e0-8a94-3a259f814854">
    <cim:IdentifiedObject.mRID>ba439cda-b55c-58e0-8a94-3a259f814854</cim:IdentifiedObject.mRID>
    <cim:IdentifiedObject.name>CB_DEPOK_L2</cim:IdentifiedObject.name>
    <cim:Equipment.EquipmentContainer rdf:resource="urn:uuid:d4853f90-2b6a-5335-bcf2-3dc12d4f703a"/>
    <cim:Equipment.inService rdf:datatype="http://www.w3.org/2001/XMLSchema#boolean">true</cim:Equipment.inService>
    <cim:Switch.open rdf:datatype="http://www.w3.org/2001/XMLSchema#boolean">false</cim:Switch.open>
    <cim:Switch.normalOpen rdf:datatype="http://www.w3.org/2001/XMLSchema#boolean">false</cim:Switch.normalOpen>
    <cim:Switch.retained rdf:datatype="http://www.w3.org/2001/XMLSchema#boolean">true</cim:Switch.retained>
  </cim:Breaker>

  <cim:Terminal rdf:about="urn:uuid:3bd142af-377c-51e5-ab79-113ed9dd3719">
    <cim:IdentifiedObject.mRID>3bd142af-377c-51e5-ab79-113ed9dd3719</cim:IdentifiedObject.mRID>
    <cim:IdentifiedObject.name>T_CB_DEPOK_L2_1</cim:IdentifiedObject.name>
    <cim:Terminal.ConductingEquipment rdf:resource="urn:uuid:ba439cda-b55c-58e0-8a94-3a259f814854"/>
    <cim:Terminal.ConnectivityNode rdf:resource="urn:uuid:1f3e1ca9-ac27-54ce-add4-7c325df64b6e"/>
    <cim:ACDCTerminal.sequenceNumber rdf:datatype="http://www.w3.org/2001/XMLSchema#integer">1</cim:ACDCTerminal.sequenceNumber>
    <cim:ACDCTerminal.connected rdf:datatype="http://www.w3.org/2001/XMLSchema#boolean">true</cim:ACDCTerminal.connected>
  </cim:Terminal>

  <cim:Terminal rdf:about="urn:uuid:6479ff7f-49c8-5a82-9941-130e70e2afa9">
    <cim:IdentifiedObject.mRID>6479ff7f-49c8-5a82-9941-130e70e2afa9</cim:IdentifiedObject.mRID>
    <cim:IdentifiedObject.name>T_CB_DEPOK_L2_2</cim:IdentifiedObject.name>
    <cim:Terminal.ConductingEquipment rdf:resource="urn:uuid:ba439cda-b55c-58e0-8a94-3a259f814854"/>
    <cim:Terminal.ConnectivityNode rdf:resource="urn:uuid:21d72021-a619-5cc0-8793-3f0339b59421"/>
    <cim:ACDCTerminal.sequenceNumber rdf:datatype="http://www.w3.org/2001/XMLSchema#integer">2</cim:ACDCTerminal.sequenceNumber>
    <cim:ACDCTerminal.connected rdf:datatype="http://www.w3.org/2001/XMLSchema#boolean">true</cim:ACDCTerminal.connected>
  </cim:Terminal>

  <cim:Breaker rdf:about="urn:uuid:6bb6d009-2a5c-5839-a80c-d4b44b900a2b">
    <cim:IdentifiedObject.mRID>6bb6d009-2a5c-5839-a80c-d4b44b900a2b</cim:IdentifiedObject.mRID>
    <cim:IdentifiedObject.name>CB_CIBINONG_T1</cim:IdentifiedObject.name>
    <cim:Equipment.EquipmentContainer rdf:resource="urn:uuid:12153ee0-6d30-5a9d-a3e8-06f2774c325c"/>
    <cim:Equipment.inService rdf:datatype="http://www.w3.org/2001/XMLSchema#boolean">true</cim:Equipment.inService>
    <cim:Switch.open rdf:datatype="http://www.w3.org/2001/XMLSchema#boolean">false</cim:Switch.open>
    <cim:Switch.normalOpen rdf:datatype="http://www.w3.org/2001/XMLSchema#boolean">false</cim:Switch.normalOpen>
    <cim:Switch.retained rdf:datatype="http://www.w3.org/2001/XMLSchema#boolean">true</cim:Switch.retained>
  </cim:Breaker>

  <cim:Terminal rdf:about="urn:uuid:00268ecd-8a2a-5a8f-bc76-3411a7cc8214">
    <cim:IdentifiedObject.mRID>00268ecd-8a2a-5a8f-bc76-3411a7cc8214</cim:IdentifiedObject.mRID>
    <cim:IdentifiedObject.name>T_CB_CIBINONG_T1_1</cim:IdentifiedObject.name>
    <cim:Terminal.ConductingEquipment rdf:resource="urn:uuid:6bb6d009-2a5c-5839-a80c-d4b44b900a2b"/>
    <cim:Terminal.ConnectivityNode rdf:resource="urn:uuid:ea2b29a1-ee88-5d8b-9823-d81e4b4862bd"/>
    <cim:ACDCTerminal.sequenceNumber rdf:datatype="http://www.w3.org/2001/XMLSchema#integer">1</cim:ACDCTerminal.sequenceNumber>
    <cim:ACDCTerminal.connected rdf:datatype="http://www.w3.org/2001/XMLSchema#boolean">true</cim:ACDCTerminal.connected>
  </cim:Terminal>

  <cim:Terminal rdf:about="urn:uuid:25917118-9808-51cd-bd8f-2bd9e6f248e9">
    <cim:IdentifiedObject.mRID>25917118-9808-51cd-bd8f-2bd9e6f248e9</cim:IdentifiedObject.mRID>
    <cim:IdentifiedObject.name>T_CB_CIBINONG_T1_2</cim:IdentifiedObject.name>
    <cim:Terminal.ConductingEquipment rdf:resource="urn:uuid:6bb6d009-2a5c-5839-a80c-d4b44b900a2b"/>
    <cim:Terminal.ConnectivityNode rdf:resource="urn:uuid:727902ba-0b84-5ec7-90db-38dc036a6d92"/>
    <cim:ACDCTerminal.sequenceNumber rdf:datatype="http://www.w3.org/2001/XMLSchema#integer">2</cim:ACDCTerminal.sequenceNumber>
    <cim:ACDCTerminal.connected rdf:datatype="http://www.w3.org/2001/XMLSchema#boolean">true</cim:ACDCTerminal.connected>
  </cim:Terminal>

  <cim:Breaker rdf:about="urn:uuid:66023ef7-0bd9-54f8-a6da-1a0588ef97a9">
    <cim:IdentifiedObject.mRID>66023ef7-0bd9-54f8-a6da-1a0588ef97a9</cim:IdentifiedObject.mRID>
    <cim:IdentifiedObject.name>CB_DEPOK_T2</cim:IdentifiedObject.name>
    <cim:Equipment.EquipmentContainer rdf:resource="urn:uuid:d4853f90-2b6a-5335-bcf2-3dc12d4f703a"/>
    <cim:Equipment.inService rdf:datatype="http://www.w3.org/2001/XMLSchema#boolean">true</cim:Equipment.inService>
    <cim:Switch.open rdf:datatype="http://www.w3.org/2001/XMLSchema#boolean">false</cim:Switch.open>
    <cim:Switch.normalOpen rdf:datatype="http://www.w3.org/2001/XMLSchema#boolean">false</cim:Switch.normalOpen>
    <cim:Switch.retained rdf:datatype="http://www.w3.org/2001/XMLSchema#boolean">true</cim:Switch.retained>
  </cim:Breaker>

  <cim:Terminal rdf:about="urn:uuid:e40e9826-23eb-5f51-b61b-74155e3bacd3">
    <cim:IdentifiedObject.mRID>e40e9826-23eb-5f51-b61b-74155e3bacd3</cim:IdentifiedObject.mRID>
    <cim:IdentifiedObject.name>T_CB_DEPOK_T2_1</cim:IdentifiedObject.name>
    <cim:Terminal.ConductingEquipment rdf:resource="urn:uuid:66023ef7-0bd9-54f8-a6da-1a0588ef97a9"/>
    <cim:Terminal.ConnectivityNode rdf:resource="urn:uuid:1f3e1ca9-ac27-54ce-add4-7c325df64b6e"/>
    <cim:ACDCTerminal.sequenceNumber rdf:datatype="http://www.w3.org/2001/XMLSchema#integer">1</cim:ACDCTerminal.sequenceNumber>
    <cim:ACDCTerminal.connected rdf:datatype="http://www.w3.org/2001/XMLSchema#boolean">true</cim:ACDCTerminal.connected>
  </cim:Terminal>

  <cim:Terminal rdf:about="urn:uuid:5431f8d0-5c4f-5c0a-adad-efc7ed7b9296">
    <cim:IdentifiedObject.mRID>5431f8d0-5c4f-5c0a-adad-efc7ed7b9296</cim:IdentifiedObject.mRID>
    <cim:IdentifiedObject.name>T_CB_DEPOK_T2_2</cim:IdentifiedObject.name>
    <cim:Terminal.ConductingEquipment rdf:resource="urn:uuid:66023ef7-0bd9-54f8-a6da-1a0588ef97a9"/>
    <cim:Terminal.ConnectivityNode rdf:resource="urn:uuid:58f59bde-fd94-5dd5-8c75-6203bfd5b59c"/>
    <cim:ACDCTerminal.sequenceNumber rdf:datatype="http://www.w3.org/2001/XMLSchema#integer">2</cim:ACDCTerminal.sequenceNumber>
    <cim:ACDCTerminal.connected rdf:datatype="http://www.w3.org/2001/XMLSchema#boolean">true</cim:ACDCTerminal.connected>
  </cim:Terminal>

  <!-- ═══ ACLineSegments ═══════════════════════════════════════════ -->
  <cim:ACLineSegment rdf:about="urn:uuid:6d16410d-9c61-5058-8370-ec34cfe1a4ed">
    <cim:IdentifiedObject.mRID>6d16410d-9c61-5058-8370-ec34cfe1a4ed</cim:IdentifiedObject.mRID>
    <cim:IdentifiedObject.name>CIRATA-CIBINONG</cim:IdentifiedObject.name>
    <cim:Equipment.EquipmentContainer rdf:resource="urn:uuid:18f93598-4ba1-5ff9-830b-b88557984275"/>
    <cim:Equipment.inService rdf:datatype="http://www.w3.org/2001/XMLSchema#boolean">true</cim:Equipment.inService>
    <cim:Conductor.length rdf:datatype="http://www.w3.org/2001/XMLSchema#float">45000.0</cim:Conductor.length>
    <cim:ACLineSegment.r rdf:datatype="http://www.w3.org/2001/XMLSchema#float">2.7135</cim:ACLineSegment.r>
    <cim:ACLineSegment.x rdf:datatype="http://www.w3.org/2001/XMLSchema#float">15.7995</cim:ACLineSegment.x>
    <cim:ACLineSegment.bch rdf:datatype="http://www.w3.org/2001/XMLSchema#float">0.000120166</cim:ACLineSegment.bch>
    <cim:ACLineSegment.gch rdf:datatype="http://www.w3.org/2001/XMLSchema#float">0.0</cim:ACLineSegment.gch>
  </cim:ACLineSegment>

  <cim:Terminal rdf:about="urn:uuid:5282b22b-c1f6-5134-8fde-3d162e1b05c1">
    <cim:IdentifiedObject.mRID>5282b22b-c1f6-5134-8fde-3d162e1b05c1</cim:IdentifiedObject.mRID>
    <cim:IdentifiedObject.name>T_CIRATA-CIBINONG_1</cim:IdentifiedObject.name>
    <cim:Terminal.ConductingEquipment rdf:resource="urn:uuid:6d16410d-9c61-5058-8370-ec34cfe1a4ed"/>
    <cim:Terminal.ConnectivityNode rdf:resource="urn:uuid:804de988-b55a-54ae-a525-115dd8d4e707"/>
    <cim:ACDCTerminal.sequenceNumber rdf:datatype="http://www.w3.org/2001/XMLSchema#integer">1</cim:ACDCTerminal.sequenceNumber>
    <cim:ACDCTerminal.connected rdf:datatype="http://www.w3.org/2001/XMLSchema#boolean">true</cim:ACDCTerminal.connected>
  </cim:Terminal>

  <cim:Terminal rdf:about="urn:uuid:b639ee6a-391a-5a9f-8368-523cf4856cff">
    <cim:IdentifiedObject.mRID>b639ee6a-391a-5a9f-8368-523cf4856cff</cim:IdentifiedObject.mRID>
    <cim:IdentifiedObject.name>T_CIRATA-CIBINONG_2</cim:IdentifiedObject.name>
    <cim:Terminal.ConductingEquipment rdf:resource="urn:uuid:6d16410d-9c61-5058-8370-ec34cfe1a4ed"/>
    <cim:Terminal.ConnectivityNode rdf:resource="urn:uuid:6c2ff010-14f3-5bfd-aded-cfdad2bf9eb3"/>
    <cim:ACDCTerminal.sequenceNumber rdf:datatype="http://www.w3.org/2001/XMLSchema#integer">2</cim:ACDCTerminal.sequenceNumber>
    <cim:ACDCTerminal.connected rdf:datatype="http://www.w3.org/2001/XMLSchema#boolean">true</cim:ACDCTerminal.connected>
  </cim:Terminal>

  <cim:ACLineSegment rdf:about="urn:uuid:64c6e9a0-a5b4-541d-8f13-c44a7cd17d77">
    <cim:IdentifiedObject.mRID>64c6e9a0-a5b4-541d-8f13-c44a7cd17d77</cim:IdentifiedObject.mRID>
    <cim:IdentifiedObject.name>CIBINONG-DEPOK</cim:IdentifiedObject.name>
    <cim:Equipment.EquipmentContainer rdf:resource="urn:uuid:12153ee0-6d30-5a9d-a3e8-06f2774c325c"/>
    <cim:Equipment.inService rdf:datatype="http://www.w3.org/2001/XMLSchema#boolean">true</cim:Equipment.inService>
    <cim:Conductor.length rdf:datatype="http://www.w3.org/2001/XMLSchema#float">32000.0</cim:Conductor.length>
    <cim:ACLineSegment.r rdf:datatype="http://www.w3.org/2001/XMLSchema#float">0.9648</cim:ACLineSegment.r>
    <cim:ACLineSegment.x rdf:datatype="http://www.w3.org/2001/XMLSchema#float">5.6176</cim:ACLineSegment.x>
    <cim:ACLineSegment.bch rdf:datatype="http://www.w3.org/2001/XMLSchema#float">0.000170903</cim:ACLineSegment.bch>
    <cim:ACLineSegment.gch rdf:datatype="http://www.w3.org/2001/XMLSchema#float">0.0</cim:ACLineSegment.gch>
  </cim:ACLineSegment>

  <cim:Terminal rdf:about="urn:uuid:e3656409-12be-59f2-b258-78de85f02f14">
    <cim:IdentifiedObject.mRID>e3656409-12be-59f2-b258-78de85f02f14</cim:IdentifiedObject.mRID>
    <cim:IdentifiedObject.name>T_CIBINONG-DEPOK_1</cim:IdentifiedObject.name>
    <cim:Terminal.ConductingEquipment rdf:resource="urn:uuid:64c6e9a0-a5b4-541d-8f13-c44a7cd17d77"/>
    <cim:Terminal.ConnectivityNode rdf:resource="urn:uuid:d61e38c9-ee84-58a3-a456-e0a63b5efeff"/>
    <cim:ACDCTerminal.sequenceNumber rdf:datatype="http://www.w3.org/2001/XMLSchema#integer">1</cim:ACDCTerminal.sequenceNumber>
    <cim:ACDCTerminal.connected rdf:datatype="http://www.w3.org/2001/XMLSchema#boolean">true</cim:ACDCTerminal.connected>
  </cim:Terminal>

  <cim:Terminal rdf:about="urn:uuid:4ac5b4db-bfaf-5557-b7a0-af92cd27105c">
    <cim:IdentifiedObject.mRID>4ac5b4db-bfaf-5557-b7a0-af92cd27105c</cim:IdentifiedObject.mRID>
    <cim:IdentifiedObject.name>T_CIBINONG-DEPOK_2</cim:IdentifiedObject.name>
    <cim:Terminal.ConductingEquipment rdf:resource="urn:uuid:64c6e9a0-a5b4-541d-8f13-c44a7cd17d77"/>
    <cim:Terminal.ConnectivityNode rdf:resource="urn:uuid:21d72021-a619-5cc0-8793-3f0339b59421"/>
    <cim:ACDCTerminal.sequenceNumber rdf:datatype="http://www.w3.org/2001/XMLSchema#integer">2</cim:ACDCTerminal.sequenceNumber>
    <cim:ACDCTerminal.connected rdf:datatype="http://www.w3.org/2001/XMLSchema#boolean">true</cim:ACDCTerminal.connected>
  </cim:Terminal>

  <cim:ACLineSegment rdf:about="urn:uuid:29f740ff-642b-5629-9a49-2fb9cc4917c0">
    <cim:IdentifiedObject.mRID>29f740ff-642b-5629-9a49-2fb9cc4917c0</cim:IdentifiedObject.mRID>
    <cim:IdentifiedObject.name>DEPOK-GANDUL</cim:IdentifiedObject.name>
    <cim:Equipment.EquipmentContainer rdf:resource="urn:uuid:d4853f90-2b6a-5335-bcf2-3dc12d4f703a"/>
    <cim:Equipment.inService rdf:datatype="http://www.w3.org/2001/XMLSchema#boolean">true</cim:Equipment.inService>
    <cim:Conductor.length rdf:datatype="http://www.w3.org/2001/XMLSchema#float">18500.0</cim:Conductor.length>
    <cim:ACLineSegment.r rdf:datatype="http://www.w3.org/2001/XMLSchema#float">1.11555</cim:ACLineSegment.r>
    <cim:ACLineSegment.x rdf:datatype="http://www.w3.org/2001/XMLSchema#float">6.49535</cim:ACLineSegment.x>
    <cim:ACLineSegment.bch rdf:datatype="http://www.w3.org/2001/XMLSchema#float">4.9402e-05</cim:ACLineSegment.bch>
    <cim:ACLineSegment.gch rdf:datatype="http://www.w3.org/2001/XMLSchema#float">0.0</cim:ACLineSegment.gch>
  </cim:ACLineSegment>

  <cim:Terminal rdf:about="urn:uuid:bbb838c6-9ec0-5f4b-be81-f5abda235c97">
    <cim:IdentifiedObject.mRID>bbb838c6-9ec0-5f4b-be81-f5abda235c97</cim:IdentifiedObject.mRID>
    <cim:IdentifiedObject.name>T_DEPOK-GANDUL_1</cim:IdentifiedObject.name>
    <cim:Terminal.ConductingEquipment rdf:resource="urn:uuid:29f740ff-642b-5629-9a49-2fb9cc4917c0"/>
    <cim:Terminal.ConnectivityNode rdf:resource="urn:uuid:1f3e1ca9-ac27-54ce-add4-7c325df64b6e"/>
    <cim:ACDCTerminal.sequenceNumber rdf:datatype="http://www.w3.org/2001/XMLSchema#integer">1</cim:ACDCTerminal.sequenceNumber>
    <cim:ACDCTerminal.connected rdf:datatype="http://www.w3.org/2001/XMLSchema#boolean">true</cim:ACDCTerminal.connected>
  </cim:Terminal>

  <cim:Terminal rdf:about="urn:uuid:11c0633c-9adb-5e9b-a8e2-1952f51c272d">
    <cim:IdentifiedObject.mRID>11c0633c-9adb-5e9b-a8e2-1952f51c272d</cim:IdentifiedObject.mRID>
    <cim:IdentifiedObject.name>T_DEPOK-GANDUL_2</cim:IdentifiedObject.name>
    <cim:Terminal.ConductingEquipment rdf:resource="urn:uuid:29f740ff-642b-5629-9a49-2fb9cc4917c0"/>
    <cim:Terminal.ConnectivityNode rdf:resource="urn:uuid:2946c071-12c0-5d7e-a0a7-26c203e85154"/>
    <cim:ACDCTerminal.sequenceNumber rdf:datatype="http://www.w3.org/2001/XMLSchema#integer">2</cim:ACDCTerminal.sequenceNumber>
    <cim:ACDCTerminal.connected rdf:datatype="http://www.w3.org/2001/XMLSchema#boolean">true</cim:ACDCTerminal.connected>
  </cim:Terminal>

  <cim:ACLineSegment rdf:about="urn:uuid:da6503f6-07b4-5647-b734-286dde5d14cb">
    <cim:IdentifiedObject.mRID>da6503f6-07b4-5647-b734-286dde5d14cb</cim:IdentifiedObject.mRID>
    <cim:IdentifiedObject.name>CIBINONG-BEKASI</cim:IdentifiedObject.name>
    <cim:Equipment.EquipmentContainer rdf:resource="urn:uuid:12153ee0-6d30-5a9d-a3e8-06f2774c325c"/>
    <cim:Equipment.inService rdf:datatype="http://www.w3.org/2001/XMLSchema#boolean">true</cim:Equipment.inService>
    <cim:Conductor.length rdf:datatype="http://www.w3.org/2001/XMLSchema#float">40000.0</cim:Conductor.length>
    <cim:ACLineSegment.r rdf:datatype="http://www.w3.org/2001/XMLSchema#float">2.412</cim:ACLineSegment.r>
    <cim:ACLineSegment.x rdf:datatype="http://www.w3.org/2001/XMLSchema#float">14.044</cim:ACLineSegment.x>
    <cim:ACLineSegment.bch rdf:datatype="http://www.w3.org/2001/XMLSchema#float">0.000106814</cim:ACLineSegment.bch>
    <cim:ACLineSegment.gch rdf:datatype="http://www.w3.org/2001/XMLSchema#float">0.0</cim:ACLineSegment.gch>
  </cim:ACLineSegment>

  <cim:Terminal rdf:about="urn:uuid:4d8452f6-9961-58df-bff3-5695bd0e0467">
    <cim:IdentifiedObject.mRID>4d8452f6-9961-58df-bff3-5695bd0e0467</cim:IdentifiedObject.mRID>
    <cim:IdentifiedObject.name>T_CIBINONG-BEKASI_1</cim:IdentifiedObject.name>
    <cim:Terminal.ConductingEquipment rdf:resource="urn:uuid:da6503f6-07b4-5647-b734-286dde5d14cb"/>
    <cim:Terminal.ConnectivityNode rdf:resource="urn:uuid:ea2b29a1-ee88-5d8b-9823-d81e4b4862bd"/>
    <cim:ACDCTerminal.sequenceNumber rdf:datatype="http://www.w3.org/2001/XMLSchema#integer">1</cim:ACDCTerminal.sequenceNumber>
    <cim:ACDCTerminal.connected rdf:datatype="http://www.w3.org/2001/XMLSchema#boolean">true</cim:ACDCTerminal.connected>
  </cim:Terminal>

  <cim:Terminal rdf:about="urn:uuid:78530acd-e45a-549e-905c-2d48ae2fe45a">
    <cim:IdentifiedObject.mRID>78530acd-e45a-549e-905c-2d48ae2fe45a</cim:IdentifiedObject.mRID>
    <cim:IdentifiedObject.name>T_CIBINONG-BEKASI_2</cim:IdentifiedObject.name>
    <cim:Terminal.ConductingEquipment rdf:resource="urn:uuid:da6503f6-07b4-5647-b734-286dde5d14cb"/>
    <cim:Terminal.ConnectivityNode rdf:resource="urn:uuid:1698b030-c9b7-5770-8e63-8bf6cff14a60"/>
    <cim:ACDCTerminal.sequenceNumber rdf:datatype="http://www.w3.org/2001/XMLSchema#integer">2</cim:ACDCTerminal.sequenceNumber>
    <cim:ACDCTerminal.connected rdf:datatype="http://www.w3.org/2001/XMLSchema#boolean">true</cim:ACDCTerminal.connected>
  </cim:Terminal>

  <cim:ACLineSegment rdf:about="urn:uuid:c074fa7d-690a-5a45-9a34-b54d7db55759">
    <cim:IdentifiedObject.mRID>c074fa7d-690a-5a45-9a34-b54d7db55759</cim:IdentifiedObject.mRID>
    <cim:IdentifiedObject.name>DEPOK-BOGOR</cim:IdentifiedObject.name>
    <cim:Equipment.EquipmentContainer rdf:resource="urn:uuid:d4853f90-2b6a-5335-bcf2-3dc12d4f703a"/>
    <cim:Equipment.inService rdf:datatype="http://www.w3.org/2001/XMLSchema#boolean">true</cim:Equipment.inService>
    <cim:Conductor.length rdf:datatype="http://www.w3.org/2001/XMLSchema#float">28000.0</cim:Conductor.length>
    <cim:ACLineSegment.r rdf:datatype="http://www.w3.org/2001/XMLSchema#float">1.6884</cim:ACLineSegment.r>
    <cim:ACLineSegment.x rdf:datatype="http://www.w3.org/2001/XMLSchema#float">9.8308</cim:ACLineSegment.x>
    <cim:ACLineSegment.bch rdf:datatype="http://www.w3.org/2001/XMLSchema#float">7.477e-05</cim:ACLineSegment.bch>
    <cim:ACLineSegment.gch rdf:datatype="http://www.w3.org/2001/XMLSchema#float">0.0</cim:ACLineSegment.gch>
  </cim:ACLineSegment>

  <cim:Terminal rdf:about="urn:uuid:ae471617-99a9-5337-aaff-478fd835faa2">
    <cim:IdentifiedObject.mRID>ae471617-99a9-5337-aaff-478fd835faa2</cim:IdentifiedObject.mRID>
    <cim:IdentifiedObject.name>T_DEPOK-BOGOR_1</cim:IdentifiedObject.name>
    <cim:Terminal.ConductingEquipment rdf:resource="urn:uuid:c074fa7d-690a-5a45-9a34-b54d7db55759"/>
    <cim:Terminal.ConnectivityNode rdf:resource="urn:uuid:1f3e1ca9-ac27-54ce-add4-7c325df64b6e"/>
    <cim:ACDCTerminal.sequenceNumber rdf:datatype="http://www.w3.org/2001/XMLSchema#integer">1</cim:ACDCTerminal.sequenceNumber>
    <cim:ACDCTerminal.connected rdf:datatype="http://www.w3.org/2001/XMLSchema#boolean">true</cim:ACDCTerminal.connected>
  </cim:Terminal>

  <cim:Terminal rdf:about="urn:uuid:e35909dc-a08a-5e51-8c22-8e15bc69e40f">
    <cim:IdentifiedObject.mRID>e35909dc-a08a-5e51-8c22-8e15bc69e40f</cim:IdentifiedObject.mRID>
    <cim:IdentifiedObject.name>T_DEPOK-BOGOR_2</cim:IdentifiedObject.name>
    <cim:Terminal.ConductingEquipment rdf:resource="urn:uuid:c074fa7d-690a-5a45-9a34-b54d7db55759"/>
    <cim:Terminal.ConnectivityNode rdf:resource="urn:uuid:115dbc85-7583-50b0-97e9-0ee2281c0967"/>
    <cim:ACDCTerminal.sequenceNumber rdf:datatype="http://www.w3.org/2001/XMLSchema#integer">2</cim:ACDCTerminal.sequenceNumber>
    <cim:ACDCTerminal.connected rdf:datatype="http://www.w3.org/2001/XMLSchema#boolean">true</cim:ACDCTerminal.connected>
  </cim:Terminal>

  <cim:ACLineSegment rdf:about="urn:uuid:727233f8-64f4-5740-b594-5541b2d15eca">
    <cim:IdentifiedObject.mRID>727233f8-64f4-5740-b594-5541b2d15eca</cim:IdentifiedObject.mRID>
    <cim:IdentifiedObject.name>GANDUL-BEKASI</cim:IdentifiedObject.name>
    <cim:Equipment.EquipmentContainer rdf:resource="urn:uuid:af5ef4f4-472e-5d58-8076-a79f26510709"/>
    <cim:Equipment.inService rdf:datatype="http://www.w3.org/2001/XMLSchema#boolean">true</cim:Equipment.inService>
    <cim:Conductor.length rdf:datatype="http://www.w3.org/2001/XMLSchema#float">22000.0</cim:Conductor.length>
    <cim:ACLineSegment.r rdf:datatype="http://www.w3.org/2001/XMLSchema#float">1.3266</cim:ACLineSegment.r>
    <cim:ACLineSegment.x rdf:datatype="http://www.w3.org/2001/XMLSchema#float">7.7242</cim:ACLineSegment.x>
    <cim:ACLineSegment.bch rdf:datatype="http://www.w3.org/2001/XMLSchema#float">5.8748e-05</cim:ACLineSegment.bch>
    <cim:ACLineSegment.gch rdf:datatype="http://www.w3.org/2001/XMLSchema#float">0.0</cim:ACLineSegment.gch>
  </cim:ACLineSegment>

  <cim:Terminal rdf:about="urn:uuid:5ef34ad3-bc9e-55fe-8ee7-c656a46f15f7">
    <cim:IdentifiedObject.mRID>5ef34ad3-bc9e-55fe-8ee7-c656a46f15f7</cim:IdentifiedObject.mRID>
    <cim:IdentifiedObject.name>T_GANDUL-BEKASI_1</cim:IdentifiedObject.name>
    <cim:Terminal.ConductingEquipment rdf:resource="urn:uuid:727233f8-64f4-5740-b594-5541b2d15eca"/>
    <cim:Terminal.ConnectivityNode rdf:resource="urn:uuid:2946c071-12c0-5d7e-a0a7-26c203e85154"/>
    <cim:ACDCTerminal.sequenceNumber rdf:datatype="http://www.w3.org/2001/XMLSchema#integer">1</cim:ACDCTerminal.sequenceNumber>
    <cim:ACDCTerminal.connected rdf:datatype="http://www.w3.org/2001/XMLSchema#boolean">true</cim:ACDCTerminal.connected>
  </cim:Terminal>

  <cim:Terminal rdf:about="urn:uuid:cbac4665-e4f5-5984-a68a-2cf23db073b4">
    <cim:IdentifiedObject.mRID>cbac4665-e4f5-5984-a68a-2cf23db073b4</cim:IdentifiedObject.mRID>
    <cim:IdentifiedObject.name>T_GANDUL-BEKASI_2</cim:IdentifiedObject.name>
    <cim:Terminal.ConductingEquipment rdf:resource="urn:uuid:727233f8-64f4-5740-b594-5541b2d15eca"/>
    <cim:Terminal.ConnectivityNode rdf:resource="urn:uuid:1698b030-c9b7-5770-8e63-8bf6cff14a60"/>
    <cim:ACDCTerminal.sequenceNumber rdf:datatype="http://www.w3.org/2001/XMLSchema#integer">2</cim:ACDCTerminal.sequenceNumber>
    <cim:ACDCTerminal.connected rdf:datatype="http://www.w3.org/2001/XMLSchema#boolean">true</cim:ACDCTerminal.connected>
  </cim:Terminal>

  <!-- ═══ PowerTransformers ════════════════════════════════════════ -->
  <cim:PowerTransformer rdf:about="urn:uuid:b1b89c4f-92de-5667-b91a-ce0a040bf2d5">
    <cim:IdentifiedObject.mRID>b1b89c4f-92de-5667-b91a-ce0a040bf2d5</cim:IdentifiedObject.mRID>
    <cim:IdentifiedObject.name>T_CIBINONG_1</cim:IdentifiedObject.name>
    <cim:Equipment.EquipmentContainer rdf:resource="urn:uuid:12153ee0-6d30-5a9d-a3e8-06f2774c325c"/>
    <cim:Equipment.inService rdf:datatype="http://www.w3.org/2001/XMLSchema#boolean">true</cim:Equipment.inService>
    <cim:PowerTransformer.isPartOfGeneratorUnit rdf:datatype="http://www.w3.org/2001/XMLSchema#boolean">false</cim:PowerTransformer.isPartOfGeneratorUnit>
  </cim:PowerTransformer>

  <cim:PowerTransformerEnd rdf:about="urn:uuid:17174415-a272-50f4-ada1-7cb3b56fdf7a">
    <cim:IdentifiedObject.mRID>17174415-a272-50f4-ada1-7cb3b56fdf7a</cim:IdentifiedObject.mRID>
    <cim:IdentifiedObject.name>T_CIBINONG_1_HV</cim:IdentifiedObject.name>
    <cim:PowerTransformerEnd.PowerTransformer rdf:resource="urn:uuid:b1b89c4f-92de-5667-b91a-ce0a040bf2d5"/>
    <cim:TransformerEnd.Terminal rdf:resource="urn:uuid:4422410c-0e53-5799-91ad-4ab88380a193"/>
    <cim:TransformerEnd.BaseVoltage rdf:resource="urn:uuid:d41fde42-d533-5df0-9005-d2c799b7dd54"/>
    <cim:TransformerEnd.endNumber rdf:datatype="http://www.w3.org/2001/XMLSchema#integer">1</cim:TransformerEnd.endNumber>
    <cim:PowerTransformerEnd.ratedS rdf:datatype="http://www.w3.org/2001/XMLSchema#float">60000000.0</cim:PowerTransformerEnd.ratedS>
    <cim:PowerTransformerEnd.ratedU rdf:datatype="http://www.w3.org/2001/XMLSchema#float">150000.0</cim:PowerTransformerEnd.ratedU>
    <cim:PowerTransformerEnd.r rdf:datatype="http://www.w3.org/2001/XMLSchema#float">1.3125</cim:PowerTransformerEnd.r>
    <cim:PowerTransformerEnd.x rdf:datatype="http://www.w3.org/2001/XMLSchema#float">46.856621</cim:PowerTransformerEnd.x>
    <cim:PowerTransformerEnd.g rdf:datatype="http://www.w3.org/2001/XMLSchema#float">2.6667e-06</cim:PowerTransformerEnd.g>
    <cim:PowerTransformerEnd.b rdf:datatype="http://www.w3.org/2001/XMLSchema#float">1.7689e-06</cim:PowerTransformerEnd.b>
    <cim:PowerTransformerEnd.phaseAngleClock rdf:datatype="http://www.w3.org/2001/XMLSchema#integer">0</cim:PowerTransformerEnd.phaseAngleClock>
  </cim:PowerTransformerEnd>

  <cim:PowerTransformerEnd rdf:about="urn:uuid:05409b57-d58b-562f-8f97-b1a81e948525">
    <cim:IdentifiedObject.mRID>05409b57-d58b-562f-8f97-b1a81e948525</cim:IdentifiedObject.mRID>
    <cim:IdentifiedObject.name>T_CIBINONG_1_LV</cim:IdentifiedObject.name>
    <cim:PowerTransformerEnd.PowerTransformer rdf:resource="urn:uuid:b1b89c4f-92de-5667-b91a-ce0a040bf2d5"/>
    <cim:TransformerEnd.Terminal rdf:resource="urn:uuid:60b2568e-2a7f-50bb-b1f1-74b23a1c760a"/>
    <cim:TransformerEnd.BaseVoltage rdf:resource="urn:uuid:9c31ca86-75f2-51ed-b0c2-8905f1317026"/>
    <cim:TransformerEnd.endNumber rdf:datatype="http://www.w3.org/2001/XMLSchema#integer">2</cim:TransformerEnd.endNumber>
    <cim:PowerTransformerEnd.ratedS rdf:datatype="http://www.w3.org/2001/XMLSchema#float">60000000.0</cim:PowerTransformerEnd.ratedS>
    <cim:PowerTransformerEnd.ratedU rdf:datatype="http://www.w3.org/2001/XMLSchema#float">20000.0</cim:PowerTransformerEnd.ratedU>
    <cim:PowerTransformerEnd.r rdf:datatype="http://www.w3.org/2001/XMLSchema#float">0.0</cim:PowerTransformerEnd.r>
    <cim:PowerTransformerEnd.x rdf:datatype="http://www.w3.org/2001/XMLSchema#float">0.0</cim:PowerTransformerEnd.x>
    <cim:PowerTransformerEnd.g rdf:datatype="http://www.w3.org/2001/XMLSchema#float">0.0</cim:PowerTransformerEnd.g>
    <cim:PowerTransformerEnd.b rdf:datatype="http://www.w3.org/2001/XMLSchema#float">0.0</cim:PowerTransformerEnd.b>
    <cim:PowerTransformerEnd.phaseAngleClock rdf:datatype="http://www.w3.org/2001/XMLSchema#integer">0</cim:PowerTransformerEnd.phaseAngleClock>
  </cim:PowerTransformerEnd>

  <cim:RatioTapChanger rdf:about="urn:uuid:e0727fa5-a03d-5ed0-a11d-d20a64bb4175">
    <cim:IdentifiedObject.mRID>e0727fa5-a03d-5ed0-a11d-d20a64bb4175</cim:IdentifiedObject.mRID>
    <cim:IdentifiedObject.name>RTC_T_CIBINONG_1</cim:IdentifiedObject.name>
    <cim:TapChanger.TransformerEnd rdf:resource="urn:uuid:17174415-a272-50f4-ada1-7cb3b56fdf7a"/>
    <cim:TapChanger.neutralStep rdf:datatype="http://www.w3.org/2001/XMLSchema#integer">0</cim:TapChanger.neutralStep>
    <cim:TapChanger.normalStep rdf:datatype="http://www.w3.org/2001/XMLSchema#integer">0</cim:TapChanger.normalStep>
    <cim:TapChanger.lowStep rdf:datatype="http://www.w3.org/2001/XMLSchema#integer">-2</cim:TapChanger.lowStep>
    <cim:TapChanger.highStep rdf:datatype="http://www.w3.org/2001/XMLSchema#integer">2</cim:TapChanger.highStep>
    <cim:TapChanger.step rdf:datatype="http://www.w3.org/2001/XMLSchema#float">0.0</cim:TapChanger.step>
    <cim:RatioTapChanger.stepVoltageIncrement rdf:datatype="http://www.w3.org/2001/XMLSchema#float">1.25</cim:RatioTapChanger.stepVoltageIncrement>
  </cim:RatioTapChanger>

  <cim:Terminal rdf:about="urn:uuid:4422410c-0e53-5799-91ad-4ab88380a193">
    <cim:IdentifiedObject.mRID>4422410c-0e53-5799-91ad-4ab88380a193</cim:IdentifiedObject.mRID>
    <cim:IdentifiedObject.name>T_T_CIBINONG_1_HV</cim:IdentifiedObject.name>
    <cim:Terminal.ConductingEquipment rdf:resource="urn:uuid:b1b89c4f-92de-5667-b91a-ce0a040bf2d5"/>
    <cim:Terminal.ConnectivityNode rdf:resource="urn:uuid:727902ba-0b84-5ec7-90db-38dc036a6d92"/>
    <cim:ACDCTerminal.sequenceNumber rdf:datatype="http://www.w3.org/2001/XMLSchema#integer">1</cim:ACDCTerminal.sequenceNumber>
    <cim:ACDCTerminal.connected rdf:datatype="http://www.w3.org/2001/XMLSchema#boolean">true</cim:ACDCTerminal.connected>
  </cim:Terminal>

  <cim:Terminal rdf:about="urn:uuid:60b2568e-2a7f-50bb-b1f1-74b23a1c760a">
    <cim:IdentifiedObject.mRID>60b2568e-2a7f-50bb-b1f1-74b23a1c760a</cim:IdentifiedObject.mRID>
    <cim:IdentifiedObject.name>T_T_CIBINONG_1_LV</cim:IdentifiedObject.name>
    <cim:Terminal.ConductingEquipment rdf:resource="urn:uuid:b1b89c4f-92de-5667-b91a-ce0a040bf2d5"/>
    <cim:Terminal.ConnectivityNode rdf:resource="urn:uuid:0ffdf116-5420-5535-baf2-3b2157e218fb"/>
    <cim:ACDCTerminal.sequenceNumber rdf:datatype="http://www.w3.org/2001/XMLSchema#integer">2</cim:ACDCTerminal.sequenceNumber>
    <cim:ACDCTerminal.connected rdf:datatype="http://www.w3.org/2001/XMLSchema#boolean">true</cim:ACDCTerminal.connected>
  </cim:Terminal>

  <cim:PowerTransformer rdf:about="urn:uuid:d444e674-7a6a-5fab-8347-70255c03632b">
    <cim:IdentifiedObject.mRID>d444e674-7a6a-5fab-8347-70255c03632b</cim:IdentifiedObject.mRID>
    <cim:IdentifiedObject.name>T_DEPOK_1</cim:IdentifiedObject.name>
    <cim:Equipment.EquipmentContainer rdf:resource="urn:uuid:d4853f90-2b6a-5335-bcf2-3dc12d4f703a"/>
    <cim:Equipment.inService rdf:datatype="http://www.w3.org/2001/XMLSchema#boolean">true</cim:Equipment.inService>
    <cim:PowerTransformer.isPartOfGeneratorUnit rdf:datatype="http://www.w3.org/2001/XMLSchema#boolean">false</cim:PowerTransformer.isPartOfGeneratorUnit>
  </cim:PowerTransformer>

  <cim:PowerTransformerEnd rdf:about="urn:uuid:ddedf477-8195-5563-9217-2833f64404f1">
    <cim:IdentifiedObject.mRID>ddedf477-8195-5563-9217-2833f64404f1</cim:IdentifiedObject.mRID>
    <cim:IdentifiedObject.name>T_DEPOK_1_HV</cim:IdentifiedObject.name>
    <cim:PowerTransformerEnd.PowerTransformer rdf:resource="urn:uuid:d444e674-7a6a-5fab-8347-70255c03632b"/>
    <cim:TransformerEnd.Terminal rdf:resource="urn:uuid:fbbce689-7958-515d-9173-bc5e1801d6a2"/>
    <cim:TransformerEnd.BaseVoltage rdf:resource="urn:uuid:d41fde42-d533-5df0-9005-d2c799b7dd54"/>
    <cim:TransformerEnd.endNumber rdf:datatype="http://www.w3.org/2001/XMLSchema#integer">1</cim:TransformerEnd.endNumber>
    <cim:PowerTransformerEnd.ratedS rdf:datatype="http://www.w3.org/2001/XMLSchema#float">100000000.0</cim:PowerTransformerEnd.ratedS>
    <cim:PowerTransformerEnd.ratedU rdf:datatype="http://www.w3.org/2001/XMLSchema#float">150000.0</cim:PowerTransformerEnd.ratedU>
    <cim:PowerTransformerEnd.r rdf:datatype="http://www.w3.org/2001/XMLSchema#float">0.7875</cim:PowerTransformerEnd.r>
    <cim:PowerTransformerEnd.x rdf:datatype="http://www.w3.org/2001/XMLSchema#float">28.113973</cim:PowerTransformerEnd.x>
    <cim:PowerTransformerEnd.g rdf:datatype="http://www.w3.org/2001/XMLSchema#float">3.5556e-06</cim:PowerTransformerEnd.g>
    <cim:PowerTransformerEnd.b rdf:datatype="http://www.w3.org/2001/XMLSchema#float">2.6667e-06</cim:PowerTransformerEnd.b>
    <cim:PowerTransformerEnd.phaseAngleClock rdf:datatype="http://www.w3.org/2001/XMLSchema#integer">0</cim:PowerTransformerEnd.phaseAngleClock>
  </cim:PowerTransformerEnd>

  <cim:PowerTransformerEnd rdf:about="urn:uuid:5c8f1da2-a26c-53a0-8dc3-f728d95361ca">
    <cim:IdentifiedObject.mRID>5c8f1da2-a26c-53a0-8dc3-f728d95361ca</cim:IdentifiedObject.mRID>
    <cim:IdentifiedObject.name>T_DEPOK_1_LV</cim:IdentifiedObject.name>
    <cim:PowerTransformerEnd.PowerTransformer rdf:resource="urn:uuid:d444e674-7a6a-5fab-8347-70255c03632b"/>
    <cim:TransformerEnd.Terminal rdf:resource="urn:uuid:3251bcad-c766-5162-8b82-b17867ed0143"/>
    <cim:TransformerEnd.BaseVoltage rdf:resource="urn:uuid:9c31ca86-75f2-51ed-b0c2-8905f1317026"/>
    <cim:TransformerEnd.endNumber rdf:datatype="http://www.w3.org/2001/XMLSchema#integer">2</cim:TransformerEnd.endNumber>
    <cim:PowerTransformerEnd.ratedS rdf:datatype="http://www.w3.org/2001/XMLSchema#float">100000000.0</cim:PowerTransformerEnd.ratedS>
    <cim:PowerTransformerEnd.ratedU rdf:datatype="http://www.w3.org/2001/XMLSchema#float">20000.0</cim:PowerTransformerEnd.ratedU>
    <cim:PowerTransformerEnd.r rdf:datatype="http://www.w3.org/2001/XMLSchema#float">0.0</cim:PowerTransformerEnd.r>
    <cim:PowerTransformerEnd.x rdf:datatype="http://www.w3.org/2001/XMLSchema#float">0.0</cim:PowerTransformerEnd.x>
    <cim:PowerTransformerEnd.g rdf:datatype="http://www.w3.org/2001/XMLSchema#float">0.0</cim:PowerTransformerEnd.g>
    <cim:PowerTransformerEnd.b rdf:datatype="http://www.w3.org/2001/XMLSchema#float">0.0</cim:PowerTransformerEnd.b>
    <cim:PowerTransformerEnd.phaseAngleClock rdf:datatype="http://www.w3.org/2001/XMLSchema#integer">0</cim:PowerTransformerEnd.phaseAngleClock>
  </cim:PowerTransformerEnd>

  <cim:RatioTapChanger rdf:about="urn:uuid:0bc72f96-c24d-5b97-a326-f4b5e7a1391e">
    <cim:IdentifiedObject.mRID>0bc72f96-c24d-5b97-a326-f4b5e7a1391e</cim:IdentifiedObject.mRID>
    <cim:IdentifiedObject.name>RTC_T_DEPOK_1</cim:IdentifiedObject.name>
    <cim:TapChanger.TransformerEnd rdf:resource="urn:uuid:ddedf477-8195-5563-9217-2833f64404f1"/>
    <cim:TapChanger.neutralStep rdf:datatype="http://www.w3.org/2001/XMLSchema#integer">0</cim:TapChanger.neutralStep>
    <cim:TapChanger.normalStep rdf:datatype="http://www.w3.org/2001/XMLSchema#integer">0</cim:TapChanger.normalStep>
    <cim:TapChanger.lowStep rdf:datatype="http://www.w3.org/2001/XMLSchema#integer">-2</cim:TapChanger.lowStep>
    <cim:TapChanger.highStep rdf:datatype="http://www.w3.org/2001/XMLSchema#integer">2</cim:TapChanger.highStep>
    <cim:TapChanger.step rdf:datatype="http://www.w3.org/2001/XMLSchema#float">0.0</cim:TapChanger.step>
    <cim:RatioTapChanger.stepVoltageIncrement rdf:datatype="http://www.w3.org/2001/XMLSchema#float">1.25</cim:RatioTapChanger.stepVoltageIncrement>
  </cim:RatioTapChanger>

  <cim:Terminal rdf:about="urn:uuid:fbbce689-7958-515d-9173-bc5e1801d6a2">
    <cim:IdentifiedObject.mRID>fbbce689-7958-515d-9173-bc5e1801d6a2</cim:IdentifiedObject.mRID>
    <cim:IdentifiedObject.name>T_T_DEPOK_1_HV</cim:IdentifiedObject.name>
    <cim:Terminal.ConductingEquipment rdf:resource="urn:uuid:d444e674-7a6a-5fab-8347-70255c03632b"/>
    <cim:Terminal.ConnectivityNode rdf:resource="urn:uuid:58f59bde-fd94-5dd5-8c75-6203bfd5b59c"/>
    <cim:ACDCTerminal.sequenceNumber rdf:datatype="http://www.w3.org/2001/XMLSchema#integer">1</cim:ACDCTerminal.sequenceNumber>
    <cim:ACDCTerminal.connected rdf:datatype="http://www.w3.org/2001/XMLSchema#boolean">true</cim:ACDCTerminal.connected>
  </cim:Terminal>

  <cim:Terminal rdf:about="urn:uuid:3251bcad-c766-5162-8b82-b17867ed0143">
    <cim:IdentifiedObject.mRID>3251bcad-c766-5162-8b82-b17867ed0143</cim:IdentifiedObject.mRID>
    <cim:IdentifiedObject.name>T_T_DEPOK_1_LV</cim:IdentifiedObject.name>
    <cim:Terminal.ConductingEquipment rdf:resource="urn:uuid:d444e674-7a6a-5fab-8347-70255c03632b"/>
    <cim:Terminal.ConnectivityNode rdf:resource="urn:uuid:e4db7411-ace7-519c-8103-b9bd48d1d95c"/>
    <cim:ACDCTerminal.sequenceNumber rdf:datatype="http://www.w3.org/2001/XMLSchema#integer">2</cim:ACDCTerminal.sequenceNumber>
    <cim:ACDCTerminal.connected rdf:datatype="http://www.w3.org/2001/XMLSchema#boolean">true</cim:ACDCTerminal.connected>
  </cim:Terminal>

  <cim:PowerTransformer rdf:about="urn:uuid:c1290090-42d7-507a-8160-b0d2a5577090">
    <cim:IdentifiedObject.mRID>c1290090-42d7-507a-8160-b0d2a5577090</cim:IdentifiedObject.mRID>
    <cim:IdentifiedObject.name>T_BEKASI_1</cim:IdentifiedObject.name>
    <cim:Equipment.EquipmentContainer rdf:resource="urn:uuid:2eceb80d-2cdf-5de7-886b-20a9f97d36bc"/>
    <cim:Equipment.inService rdf:datatype="http://www.w3.org/2001/XMLSchema#boolean">true</cim:Equipment.inService>
    <cim:PowerTransformer.isPartOfGeneratorUnit rdf:datatype="http://www.w3.org/2001/XMLSchema#boolean">false</cim:PowerTransformer.isPartOfGeneratorUnit>
  </cim:PowerTransformer>

  <cim:PowerTransformerEnd rdf:about="urn:uuid:41e54680-2393-5071-8478-5e42d18a8c15">
    <cim:IdentifiedObject.mRID>41e54680-2393-5071-8478-5e42d18a8c15</cim:IdentifiedObject.mRID>
    <cim:IdentifiedObject.name>T_BEKASI_1_HV</cim:IdentifiedObject.name>
    <cim:PowerTransformerEnd.PowerTransformer rdf:resource="urn:uuid:c1290090-42d7-507a-8160-b0d2a5577090"/>
    <cim:TransformerEnd.Terminal rdf:resource="urn:uuid:e0d2c29b-dff2-5000-b584-464f48ecb3ac"/>
    <cim:TransformerEnd.BaseVoltage rdf:resource="urn:uuid:d41fde42-d533-5df0-9005-d2c799b7dd54"/>
    <cim:TransformerEnd.endNumber rdf:datatype="http://www.w3.org/2001/XMLSchema#integer">1</cim:TransformerEnd.endNumber>
    <cim:PowerTransformerEnd.ratedS rdf:datatype="http://www.w3.org/2001/XMLSchema#float">60000000.0</cim:PowerTransformerEnd.ratedS>
    <cim:PowerTransformerEnd.ratedU rdf:datatype="http://www.w3.org/2001/XMLSchema#float">150000.0</cim:PowerTransformerEnd.ratedU>
    <cim:PowerTransformerEnd.r rdf:datatype="http://www.w3.org/2001/XMLSchema#float">1.3125</cim:PowerTransformerEnd.r>
    <cim:PowerTransformerEnd.x rdf:datatype="http://www.w3.org/2001/XMLSchema#float">46.856621</cim:PowerTransformerEnd.x>
    <cim:PowerTransformerEnd.g rdf:datatype="http://www.w3.org/2001/XMLSchema#float">2.6667e-06</cim:PowerTransformerEnd.g>
    <cim:PowerTransformerEnd.b rdf:datatype="http://www.w3.org/2001/XMLSchema#float">1.7689e-06</cim:PowerTransformerEnd.b>
    <cim:PowerTransformerEnd.phaseAngleClock rdf:datatype="http://www.w3.org/2001/XMLSchema#integer">0</cim:PowerTransformerEnd.phaseAngleClock>
  </cim:PowerTransformerEnd>

  <cim:PowerTransformerEnd rdf:about="urn:uuid:612bebc6-6207-513b-a462-76b4e97ff603">
    <cim:IdentifiedObject.mRID>612bebc6-6207-513b-a462-76b4e97ff603</cim:IdentifiedObject.mRID>
    <cim:IdentifiedObject.name>T_BEKASI_1_LV</cim:IdentifiedObject.name>
    <cim:PowerTransformerEnd.PowerTransformer rdf:resource="urn:uuid:c1290090-42d7-507a-8160-b0d2a5577090"/>
    <cim:TransformerEnd.Terminal rdf:resource="urn:uuid:ddc14e4a-4e92-57ab-8500-3930910bc543"/>
    <cim:TransformerEnd.BaseVoltage rdf:resource="urn:uuid:9c31ca86-75f2-51ed-b0c2-8905f1317026"/>
    <cim:TransformerEnd.endNumber rdf:datatype="http://www.w3.org/2001/XMLSchema#integer">2</cim:TransformerEnd.endNumber>
    <cim:PowerTransformerEnd.ratedS rdf:datatype="http://www.w3.org/2001/XMLSchema#float">60000000.0</cim:PowerTransformerEnd.ratedS>
    <cim:PowerTransformerEnd.ratedU rdf:datatype="http://www.w3.org/2001/XMLSchema#float">20000.0</cim:PowerTransformerEnd.ratedU>
    <cim:PowerTransformerEnd.r rdf:datatype="http://www.w3.org/2001/XMLSchema#float">0.0</cim:PowerTransformerEnd.r>
    <cim:PowerTransformerEnd.x rdf:datatype="http://www.w3.org/2001/XMLSchema#float">0.0</cim:PowerTransformerEnd.x>
    <cim:PowerTransformerEnd.g rdf:datatype="http://www.w3.org/2001/XMLSchema#float">0.0</cim:PowerTransformerEnd.g>
    <cim:PowerTransformerEnd.b rdf:datatype="http://www.w3.org/2001/XMLSchema#float">0.0</cim:PowerTransformerEnd.b>
    <cim:PowerTransformerEnd.phaseAngleClock rdf:datatype="http://www.w3.org/2001/XMLSchema#integer">0</cim:PowerTransformerEnd.phaseAngleClock>
  </cim:PowerTransformerEnd>

  <cim:RatioTapChanger rdf:about="urn:uuid:8591622c-d48b-5a1e-988a-3db082b29a10">
    <cim:IdentifiedObject.mRID>8591622c-d48b-5a1e-988a-3db082b29a10</cim:IdentifiedObject.mRID>
    <cim:IdentifiedObject.name>RTC_T_BEKASI_1</cim:IdentifiedObject.name>
    <cim:TapChanger.TransformerEnd rdf:resource="urn:uuid:41e54680-2393-5071-8478-5e42d18a8c15"/>
    <cim:TapChanger.neutralStep rdf:datatype="http://www.w3.org/2001/XMLSchema#integer">0</cim:TapChanger.neutralStep>
    <cim:TapChanger.normalStep rdf:datatype="http://www.w3.org/2001/XMLSchema#integer">0</cim:TapChanger.normalStep>
    <cim:TapChanger.lowStep rdf:datatype="http://www.w3.org/2001/XMLSchema#integer">-2</cim:TapChanger.lowStep>
    <cim:TapChanger.highStep rdf:datatype="http://www.w3.org/2001/XMLSchema#integer">2</cim:TapChanger.highStep>
    <cim:TapChanger.step rdf:datatype="http://www.w3.org/2001/XMLSchema#float">0.0</cim:TapChanger.step>
    <cim:RatioTapChanger.stepVoltageIncrement rdf:datatype="http://www.w3.org/2001/XMLSchema#float">1.25</cim:RatioTapChanger.stepVoltageIncrement>
  </cim:RatioTapChanger>

  <cim:Terminal rdf:about="urn:uuid:e0d2c29b-dff2-5000-b584-464f48ecb3ac">
    <cim:IdentifiedObject.mRID>e0d2c29b-dff2-5000-b584-464f48ecb3ac</cim:IdentifiedObject.mRID>
    <cim:IdentifiedObject.name>T_T_BEKASI_1_HV</cim:IdentifiedObject.name>
    <cim:Terminal.ConductingEquipment rdf:resource="urn:uuid:c1290090-42d7-507a-8160-b0d2a5577090"/>
    <cim:Terminal.ConnectivityNode rdf:resource="urn:uuid:1698b030-c9b7-5770-8e63-8bf6cff14a60"/>
    <cim:ACDCTerminal.sequenceNumber rdf:datatype="http://www.w3.org/2001/XMLSchema#integer">1</cim:ACDCTerminal.sequenceNumber>
    <cim:ACDCTerminal.connected rdf:datatype="http://www.w3.org/2001/XMLSchema#boolean">true</cim:ACDCTerminal.connected>
  </cim:Terminal>

  <cim:Terminal rdf:about="urn:uuid:ddc14e4a-4e92-57ab-8500-3930910bc543">
    <cim:IdentifiedObject.mRID>ddc14e4a-4e92-57ab-8500-3930910bc543</cim:IdentifiedObject.mRID>
    <cim:IdentifiedObject.name>T_T_BEKASI_1_LV</cim:IdentifiedObject.name>
    <cim:Terminal.ConductingEquipment rdf:resource="urn:uuid:c1290090-42d7-507a-8160-b0d2a5577090"/>
    <cim:Terminal.ConnectivityNode rdf:resource="urn:uuid:2ed59b45-5650-5677-9958-5d9b2dffe1dc"/>
    <cim:ACDCTerminal.sequenceNumber rdf:datatype="http://www.w3.org/2001/XMLSchema#integer">2</cim:ACDCTerminal.sequenceNumber>
    <cim:ACDCTerminal.connected rdf:datatype="http://www.w3.org/2001/XMLSchema#boolean">true</cim:ACDCTerminal.connected>
  </cim:Terminal>

  <cim:PowerTransformer rdf:about="urn:uuid:2d5f4377-c8fc-51bd-bd35-8080a1e42f6f">
    <cim:IdentifiedObject.mRID>2d5f4377-c8fc-51bd-bd35-8080a1e42f6f</cim:IdentifiedObject.mRID>
    <cim:IdentifiedObject.name>T_BOGOR_1</cim:IdentifiedObject.name>
    <cim:Equipment.EquipmentContainer rdf:resource="urn:uuid:d5030fdf-26e6-5862-9072-263636e89021"/>
    <cim:Equipment.inService rdf:datatype="http://www.w3.org/2001/XMLSchema#boolean">true</cim:Equipment.inService>
    <cim:PowerTransformer.isPartOfGeneratorUnit rdf:datatype="http://www.w3.org/2001/XMLSchema#boolean">false</cim:PowerTransformer.isPartOfGeneratorUnit>
  </cim:PowerTransformer>

  <cim:PowerTransformerEnd rdf:about="urn:uuid:3c71585d-aade-5864-9b8a-0a12ba833b9d">
    <cim:IdentifiedObject.mRID>3c71585d-aade-5864-9b8a-0a12ba833b9d</cim:IdentifiedObject.mRID>
    <cim:IdentifiedObject.name>T_BOGOR_1_HV</cim:IdentifiedObject.name>
    <cim:PowerTransformerEnd.PowerTransformer rdf:resource="urn:uuid:2d5f4377-c8fc-51bd-bd35-8080a1e42f6f"/>
    <cim:TransformerEnd.Terminal rdf:resource="urn:uuid:266cf3df-43b6-5af8-8c46-97ca9c84e53a"/>
    <cim:TransformerEnd.BaseVoltage rdf:resource="urn:uuid:d41fde42-d533-5df0-9005-d2c799b7dd54"/>
    <cim:TransformerEnd.endNumber rdf:datatype="http://www.w3.org/2001/XMLSchema#integer">1</cim:TransformerEnd.endNumber>
    <cim:PowerTransformerEnd.ratedS rdf:datatype="http://www.w3.org/2001/XMLSchema#float">60000000.0</cim:PowerTransformerEnd.ratedS>
    <cim:PowerTransformerEnd.ratedU rdf:datatype="http://www.w3.org/2001/XMLSchema#float">150000.0</cim:PowerTransformerEnd.ratedU>
    <cim:PowerTransformerEnd.r rdf:datatype="http://www.w3.org/2001/XMLSchema#float">1.3125</cim:PowerTransformerEnd.r>
    <cim:PowerTransformerEnd.x rdf:datatype="http://www.w3.org/2001/XMLSchema#float">46.856621</cim:PowerTransformerEnd.x>
    <cim:PowerTransformerEnd.g rdf:datatype="http://www.w3.org/2001/XMLSchema#float">2.6667e-06</cim:PowerTransformerEnd.g>
    <cim:PowerTransformerEnd.b rdf:datatype="http://www.w3.org/2001/XMLSchema#float">1.7689e-06</cim:PowerTransformerEnd.b>
    <cim:PowerTransformerEnd.phaseAngleClock rdf:datatype="http://www.w3.org/2001/XMLSchema#integer">0</cim:PowerTransformerEnd.phaseAngleClock>
  </cim:PowerTransformerEnd>

  <cim:PowerTransformerEnd rdf:about="urn:uuid:f6ef22bb-7f32-5573-8d5c-f71452304183">
    <cim:IdentifiedObject.mRID>f6ef22bb-7f32-5573-8d5c-f71452304183</cim:IdentifiedObject.mRID>
    <cim:IdentifiedObject.name>T_BOGOR_1_LV</cim:IdentifiedObject.name>
    <cim:PowerTransformerEnd.PowerTransformer rdf:resource="urn:uuid:2d5f4377-c8fc-51bd-bd35-8080a1e42f6f"/>
    <cim:TransformerEnd.Terminal rdf:resource="urn:uuid:5baafcf5-0c05-5c9d-b7f4-2303c67fe2f8"/>
    <cim:TransformerEnd.BaseVoltage rdf:resource="urn:uuid:9c31ca86-75f2-51ed-b0c2-8905f1317026"/>
    <cim:TransformerEnd.endNumber rdf:datatype="http://www.w3.org/2001/XMLSchema#integer">2</cim:TransformerEnd.endNumber>
    <cim:PowerTransformerEnd.ratedS rdf:datatype="http://www.w3.org/2001/XMLSchema#float">60000000.0</cim:PowerTransformerEnd.ratedS>
    <cim:PowerTransformerEnd.ratedU rdf:datatype="http://www.w3.org/2001/XMLSchema#float">20000.0</cim:PowerTransformerEnd.ratedU>
    <cim:PowerTransformerEnd.r rdf:datatype="http://www.w3.org/2001/XMLSchema#float">0.0</cim:PowerTransformerEnd.r>
    <cim:PowerTransformerEnd.x rdf:datatype="http://www.w3.org/2001/XMLSchema#float">0.0</cim:PowerTransformerEnd.x>
    <cim:PowerTransformerEnd.g rdf:datatype="http://www.w3.org/2001/XMLSchema#float">0.0</cim:PowerTransformerEnd.g>
    <cim:PowerTransformerEnd.b rdf:datatype="http://www.w3.org/2001/XMLSchema#float">0.0</cim:PowerTransformerEnd.b>
    <cim:PowerTransformerEnd.phaseAngleClock rdf:datatype="http://www.w3.org/2001/XMLSchema#integer">0</cim:PowerTransformerEnd.phaseAngleClock>
  </cim:PowerTransformerEnd>

  <cim:RatioTapChanger rdf:about="urn:uuid:86a4a55c-9042-5d68-bd87-e4eacbeb2961">
    <cim:IdentifiedObject.mRID>86a4a55c-9042-5d68-bd87-e4eacbeb2961</cim:IdentifiedObject.mRID>
    <cim:IdentifiedObject.name>RTC_T_BOGOR_1</cim:IdentifiedObject.name>
    <cim:TapChanger.TransformerEnd rdf:resource="urn:uuid:3c71585d-aade-5864-9b8a-0a12ba833b9d"/>
    <cim:TapChanger.neutralStep rdf:datatype="http://www.w3.org/2001/XMLSchema#integer">0</cim:TapChanger.neutralStep>
    <cim:TapChanger.normalStep rdf:datatype="http://www.w3.org/2001/XMLSchema#integer">0</cim:TapChanger.normalStep>
    <cim:TapChanger.lowStep rdf:datatype="http://www.w3.org/2001/XMLSchema#integer">-2</cim:TapChanger.lowStep>
    <cim:TapChanger.highStep rdf:datatype="http://www.w3.org/2001/XMLSchema#integer">2</cim:TapChanger.highStep>
    <cim:TapChanger.step rdf:datatype="http://www.w3.org/2001/XMLSchema#float">0.0</cim:TapChanger.step>
    <cim:RatioTapChanger.stepVoltageIncrement rdf:datatype="http://www.w3.org/2001/XMLSchema#float">1.25</cim:RatioTapChanger.stepVoltageIncrement>
  </cim:RatioTapChanger>

  <cim:Terminal rdf:about="urn:uuid:266cf3df-43b6-5af8-8c46-97ca9c84e53a">
    <cim:IdentifiedObject.mRID>266cf3df-43b6-5af8-8c46-97ca9c84e53a</cim:IdentifiedObject.mRID>
    <cim:IdentifiedObject.name>T_T_BOGOR_1_HV</cim:IdentifiedObject.name>
    <cim:Terminal.ConductingEquipment rdf:resource="urn:uuid:2d5f4377-c8fc-51bd-bd35-8080a1e42f6f"/>
    <cim:Terminal.ConnectivityNode rdf:resource="urn:uuid:115dbc85-7583-50b0-97e9-0ee2281c0967"/>
    <cim:ACDCTerminal.sequenceNumber rdf:datatype="http://www.w3.org/2001/XMLSchema#integer">1</cim:ACDCTerminal.sequenceNumber>
    <cim:ACDCTerminal.connected rdf:datatype="http://www.w3.org/2001/XMLSchema#boolean">true</cim:ACDCTerminal.connected>
  </cim:Terminal>

  <cim:Terminal rdf:about="urn:uuid:5baafcf5-0c05-5c9d-b7f4-2303c67fe2f8">
    <cim:IdentifiedObject.mRID>5baafcf5-0c05-5c9d-b7f4-2303c67fe2f8</cim:IdentifiedObject.mRID>
    <cim:IdentifiedObject.name>T_T_BOGOR_1_LV</cim:IdentifiedObject.name>
    <cim:Terminal.ConductingEquipment rdf:resource="urn:uuid:2d5f4377-c8fc-51bd-bd35-8080a1e42f6f"/>
    <cim:Terminal.ConnectivityNode rdf:resource="urn:uuid:90035e27-51c2-54fb-8d8c-c6ba0539c67d"/>
    <cim:ACDCTerminal.sequenceNumber rdf:datatype="http://www.w3.org/2001/XMLSchema#integer">2</cim:ACDCTerminal.sequenceNumber>
    <cim:ACDCTerminal.connected rdf:datatype="http://www.w3.org/2001/XMLSchema#boolean">true</cim:ACDCTerminal.connected>
  </cim:Terminal>

</rdf:RDF>
